Workbook
Name Slicer_Market: #N/A

Sheet Purchase Orders
A1: PO ID | B1: SKU | C1: Supplier ID | D1: Order Date | E1: Expected Date | F1: Actual Delivery Date | G1: Units Ordered | H1: Unit Purchase Cost | I1: PO Status
A2: PO-00258 | B2: SKU-0005 | C2: SUP-006 | D2: 45932 | E2: 45937 | F2: 45935 | G2: 125 | H2: 25.85 | I2: Received
A3: PO-00220 | B3: SKU-0009 | C3: SUP-001 | D3: 45933 | E3: 45939 | F3: 45939 | G3: 40 | H3: 36.44 | I3: Received
A4: PO-00317 | B4: SKU-0013 | C4: SUP-002 | D4: 45933 | E4: 45945 | F4: 45945 | G4: 75 | H4: 21.33 | I4: Received
A5: PO-00107 | B5: SKU-0007 | C5: SUP-001 | D5: 45934 | E5: 45940 | F5: 45940 | G5: 60 | H5: 7.24 | I5: Received
A6: PO-00205 | B6: SKU-0038 | C6: SUP-004 | D6: 45942 | E6: 45949 | F6: 45947 | G6: 60 | H6: 41.96 | I6: Received
A7: PO-00312 | B7: SKU-0054 | C7: SUP-005 | D7: 45942 | E7: 45957 | F7: 45957 | G7: 100 | H7: 30.61 | I7: Received
A8: PO-00147 | B8: SKU-0003 | C8: SUP-011 | D8: 45943 | E8: 45953 | F8: 45953 | G8: 75 | H8: 6.46 | I8: Received
A9: PO-00001 | B9: SKU-0024 | C9: SUP-002 | D9: 45946 | E9: 45958 | G9: 100 | H9: 40.34 | I9: Cancelled
A10: PO-00044 | B10: SKU-0037 | C10: SUP-009 | D10: 45949 | E10: 45953 | F10: 45954 | G10: 125 | H10: 13.85 | I10: Received
A11: PO-00185 | B11: SKU-0046 | C11: SUP-009 | D11: 45949 | E11: 45953 | F11: 45953 | G11: 30 | H11: 19.49 | I11: Received
A12: PO-00264 | B12: SKU-0055 | C12: SUP-005 | D12: 45950 | E12: 45965 | F12: 45972 | G12: 50 | H12: 4.93 | I12: Received
A13: PO-00057 | B13: SKU-0020 | C13: SUP-002 | D13: 45952 | E13: 45964 | F13: 45964 | G13: 40 | H13: 43.46 | I13: Received
A14: PO-00095 | B14: SKU-0018 | C14: SUP-002 | D14: 45952 | E14: 45964 | F14: 45964 | G14: 40 | H14: 7.75 | I14: Received
A15: PO-00269 | B15: SKU-0060 | C15: SUP-010 | D15: 45957 | E15: 45970 | F15: 45971 | G15: 75 | H15: 31.07 | I15: Received
A16: PO-00179 | B16: SKU-0033 | C16: SUP-003 | D16: 45958 | E16: 45967 | F16: 45967 | G16: 50 | H16: 45 | I16: Received
A17: PO-00278 | B17: SKU-0054 | C17: SUP-005 | D17: 45960 | E17: 45975 | F17: 45975 | G17: 60 | H17: 30.61 | I17: Received
A18: PO-00280 | B18: SKU-0007 | C18: SUP-001 | D18: 45963 | E18: 45969 | F18: 45969 | G18: 30 | H18: 7.24 | I18: Received
A19: PO-00026 | B19: SKU-0027 | C19: SUP-012 | D19: 45964 | E19: 45978 | F19: 45978 | G19: 40 | H19: 17.22 | I19: Received
A20: PO-00098 | B20: SKU-0011 | C20: SUP-011 | D20: 45966 | E20: 45976 | F20: 45976 | G20: 30 | H20: 24.06 | I20: Received
A21: PO-00330 | B21: SKU-0046 | C21: SUP-009 | D21: 45967 | E21: 45971 | F21: 45972 | G21: 30 | H21: 19.49 | I21: Received
A22: PO-00140 | B22: SKU-0042 | C22: SUP-004 | D22: 45968 | E22: 45975 | G22: 60 | H22: 28.8 | I22: Open
A23: PO-00178 | B23: SKU-0012 | C23: SUP-011 | D23: 45968 | E23: 45978 | F23: 45979 | G23: 100 | H23: 34.53 | I23: Received
A24: PO-00209 | B24: SKU-0042 | C24: SUP-004 | D24: 45968 | E24: 45975 | F24: 45977 | G24: 30 | H24: 28.8 | I24: Received
A25: PO-00043 | B25: SKU-0018 | C25: SUP-002 | D25: 45969 | E25: 45981 | G25: 60 | H25: 7.75 | I25: Open
A26: PO-00283 | B26: SKU-0038 | C26: SUP-004 | D26: 45969 | E26: 45976 | G26: 125 | H26: 41.96 | I26: Open
A27: PO-00091 | B27: SKU-0010 | C27: SUP-011 | D27: 45970 | E27: 45980 | G27: 100 | H27: 8.53 | I27: Cancelled
A28: PO-00033 | B28: SKU-0056 | C28: SUP-010 | D28: 45971 | E28: 45984 | G28: 20 | H28: 44.67 | I28: Open
A29: PO-00102 | B29: SKU-0047 | C29: SUP-009 | D29: 45972 | E29: 45976 | F29: 45976 | G29: 100 | H29: 21.05 | I29: Received
A30: PO-00251 | B30: SKU-0004 | C30: SUP-006 | D30: 45973 | E30: 45978 | G30: 50 | H30: 11.55 | I30: Open
A31: PO-00016 | B31: SKU-0059 | C31: SUP-005 | D31: 45974 | E31: 45989 | F31: 45987 | G31: 100 | H31: 18.04 | I31: Received
A32: PO-00047 | B32: SKU-0007 | C32: SUP-001 | D32: 45974 | E32: 45980 | F32: 45979 | G32: 75 | H32: 7.24 | I32: Received
A33: PO-00247 | B33: SKU-0030 | C33: SUP-003 | D33: 45975 | E33: 45984 | F33: 45984 | G33: 50 | H33: 23.48 | I33: Received
A34: PO-00198 | B34: SKU-0018 | C34: SUP-002 | D34: 45976 | E34: 45988 | F34: 45989 | G34: 40 | H34: 7.75 | I34: Received
A35: PO-00243 | B35: SKU-0005 | C35: SUP-006 | D35: 45980 | E35: 45985 | G35: 75 | H35: 25.85 | I35: Open
A36: PO-00325 | B36: SKU-0006 | C36: SUP-001 | D36: 45981 | E36: 45987 | G36: 75 | H36: 21.34 | I36: Cancelled
A37: PO-00201 | B37: SKU-0043 | C37: SUP-004 | D37: 45983 | E37: 45990 | F37: 45997 | G37: 60 | H37: 19.66 | I37: Received
A38: PO-00090 | B38: SKU-0032 | C38: SUP-012 | D38: 45984 | E38: 45998 | F38: 45999 | G38: 75 | H38: 4.42 | I38: Received
A39: PO-00041 | B39: SKU-0028 | C39: SUP-008 | D39: 45985 | E39: 45993 | F39: 45995 | G39: 20 | H39: 17.55 | I39: Received
A40: PO-00117 | B40: SKU-0011 | C40: SUP-011 | D40: 45985 | E40: 45995 | F40: 45997 | G40: 75 | H40: 24.06 | I40: Received
A41: PO-00169 | B41: SKU-0037 | C41: SUP-009 | D41: 45986 | E41: 45990 | F41: 45990 | G41: 50 | H41: 13.85 | I41: Received
A42: PO-00250 | B42: SKU-0023 | C42: SUP-007 | D42: 45986 | E42: 45997 | F42: 45996 | G42: 30 | H42: 23.26 | I42: Received
A43: PO-00017 | B43: SKU-0044 | C43: SUP-009 | D43: 45988 | E43: 45992 | F43: 45991 | G43: 125 | H43: 41.46 | I43: Received
A44: PO-00298 | B44: SKU-0022 | C44: SUP-007 | D44: 45989 | E44: 46000 | F44: 46000 | G44: 100 | H44: 21.59 | I44: Received
A45: PO-00153 | B45: SKU-0052 | C45: SUP-005 | D45: 45991 | E45: 46006 | F45: 46007 | G45: 125 | H45: 18.73 | I45: Received
A46: PO-00080 | B46: SKU-0051 | C46: SUP-010 | D46: 45992 | E46: 46005 | G46: 100 | H46: 23.03 | I46: Open
A47: PO-00288 | B47: SKU-0030 | C47: SUP-003 | D47: 45992 | E47: 46001 | F47: 46005 | G47: 100 | H47: 23.48 | I47: Received
A48: PO-00304 | B48: SKU-0054 | C48: SUP-005 | D48: 45993 | E48: 46008 | F48: 46008 | G48: 40 | H48: 30.61 | I48: Received
A49: PO-00268 | B49: SKU-0006 | C49: SUP-001 | D49: 45994 | E49: 46000 | F49: 46000 | G49: 20 | H49: 21.34 | I49: Received
A50: PO-00019 | B50: SKU-0007 | C50: SUP-001 | D50: 45995 | E50: 46001 | F50: 46003 | G50: 60 | H50: 7.24 | I50: Received
A51: PO-00287 | B51: SKU-0028 | C51: SUP-008 | D51: 45995 | E51: 46003 | G51: 75 | H51: 17.55 | I51: Open
A52: PO-00199 | B52: SKU-0049 | C52: SUP-010 | D52: 45996 | E52: 46009 | G52: 60 | H52: 39.76 | I52: Open
A53: PO-00204 | B53: SKU-0031 | C53: SUP-012 | D53: 45997 | E53: 46011 | F53: 46011 | G53: 40 | H53: 36.28 | I53: Received
A54: PO-00006 | B54: SKU-0025 | C54: SUP-003 | D54: 45998 | E54: 46007 | G54: 125 | H54: 13.41 | I54: Open
A55: PO-00232 | B55: SKU-0005 | C55: SUP-006 | D55: 46000 | E55: 46005 | F55: 46009 | G55: 125 | H55: 25.85 | I55: Received
A56: PO-00323 | B56: SKU-0036 | C56: SUP-003 | D56: 46000 | E56: 46009 | F56: 46010 | G56: 60 | H56: 37.14 | I56: Received
A57: PO-00200 | B57: SKU-0023 | C57: SUP-007 | D57: 46001 | E57: 46012 | G57: 75 | H57: 23.26 | I57: Open
A58: PO-00194 | B58: SKU-0034 | C58: SUP-008 | D58: 46002 | E58: 46010 | F58: 46009 | G58: 60 | H58: 22.11 | I58: Received
A59: PO-00120 | B59: SKU-0055 | C59: SUP-005 | D59: 46004 | E59: 46019 | F59: 46019 | G59: 75 | H59: 4.93 | I59: Received
A60: PO-00106 | B60: SKU-0023 | C60: SUP-007 | D60: 46005 | E60: 46016 | F60: 46020 | G60: 100 | H60: 23.26 | I60: Received
A61: PO-00244 | B61: SKU-0032 | C61: SUP-012 | D61: 46006 | E61: 46020 | F61: 46020 | G61: 60 | H61: 4.42 | I61: Received
A62: PO-00129 | B62: SKU-0057 | C62: SUP-010 | D62: 46009 | E62: 46022 | F62: 46023 | G62: 60 | H62: 25.69 | I62: Received
A63: PO-00020 | B63: SKU-0038 | C63: SUP-004 | D63: 46010 | E63: 46017 | F63: 46016 | G63: 30 | H63: 41.96 | I63: Received
A64: PO-00075 | B64: SKU-0049 | C64: SUP-010 | D64: 46010 | E64: 46023 | F64: 46024 | G64: 40 | H64: 39.76 | I64: Received
A65: PO-00217 | B65: SKU-0031 | C65: SUP-012 | D65: 46011 | E65: 46025 | F65: 46026 | G65: 20 | H65: 36.28 | I65: Received
A66: PO-00122 | B66: SKU-0021 | C66: SUP-002 | D66: 46014 | E66: 46026 | F66: 46027 | G66: 20 | H66: 13.98 | I66: Received
A67: PO-00051 | B67: SKU-0044 | C67: SUP-009 | D67: 46015 | E67: 46019 | F67: 46023 | G67: 100 | H67: 41.46 | I67: Received
A68: PO-00159 | B68: SKU-0023 | C68: SUP-007 | D68: 46016 | E68: 46027 | F68: 46025 | G68: 125 | H68: 23.26 | I68: Received
A69: PO-00265 | B69: SKU-0028 | C69: SUP-008 | D69: 46017 | E69: 46025 | G69: 60 | H69: 17.55 | I69: Open
A70: PO-00321 | B70: SKU-0005 | C70: SUP-006 | D70: 46017 | E70: 46022 | F70: 46022 | G70: 40 | H70: 25.85 | I70: Received
A71: PO-00231 | B71: SKU-0047 | C71: SUP-009 | D71: 46018 | E71: 46022 | F71: 46022 | G71: 20 | H71: 21.05 | I71: Received
A72: PO-00138 | B72: SKU-0032 | C72: SUP-012 | D72: 46019 | E72: 46033 | F72: 46037 | G72: 100 | H72: 4.42 | I72: Received
A73: PO-00246 | B73: SKU-0057 | C73: SUP-010 | D73: 46020 | E73: 46033 | F73: 46033 | G73: 100 | H73: 25.69 | I73: Received
A74: PO-00166 | B74: SKU-0043 | C74: SUP-004 | D74: 46023 | E74: 46030 | F74: 46031 | G74: 40 | H74: 19.66 | I74: Received
A75: PO-00163 | B75: SKU-0056 | C75: SUP-010 | D75: 46024 | E75: 46037 | F75: 46035 | G75: 100 | H75: 44.67 | I75: Received
A76: PO-00052 | B76: SKU-0017 | C76: SUP-002 | D76: 46025 | E76: 46037 | F76: 46036 | G76: 40 | H76: 31.21 | I76: Received
A77: PO-00110 | B77: SKU-0027 | C77: SUP-012 | D77: 46025 | E77: 46039 | F77: 46040 | G77: 100 | H77: 17.22 | I77: Received
A78: PO-00242 | B78: SKU-0043 | C78: SUP-004 | D78: 46025 | E78: 46032 | G78: 50 | H78: 19.66 | I78: Open
A79: PO-00124 | B79: SKU-0031 | C79: SUP-012 | D79: 46027 | E79: 46041 | G79: 50 | H79: 36.28 | I79: Open
A80: PO-00058 | B80: SKU-0002 | C80: SUP-001 | D80: 46028 | E80: 46034 | F80: 46038 | G80: 100 | H80: 37 | I80: Received
A81: PO-00286 | B81: SKU-0040 | C81: SUP-009 | D81: 46028 | E81: 46032 | F81: 46034 | G81: 50 | H81: 17.33 | I81: Received
A82: PO-00131 | B82: SKU-0050 | C82: SUP-010 | D82: 46030 | E82: 46043 | F82: 46050 | G82: 50 | H82: 18.54 | I82: Received
A83: PO-00086 | B83: SKU-0042 | C83: SUP-004 | D83: 46031 | E83: 46038 | F83: 46037 | G83: 100 | H83: 28.8 | I83: Received
A84: PO-00245 | B84: SKU-0012 | C84: SUP-011 | D84: 46032 | E84: 46042 | F84: 46039 | G84: 40 | H84: 34.53 | I84: Received
A85: PO-00038 | B85: SKU-0017 | C85: SUP-002 | D85: 46034 | E85: 46046 | F85: 46050 | G85: 50 | H85: 31.21 | I85: Received
A86: PO-00096 | B86: SKU-0053 | C86: SUP-010 | D86: 46034 | E86: 46047 | F86: 46047 | G86: 50 | H86: 44.56 | I86: Received
A87: PO-00060 | B87: SKU-0032 | C87: SUP-012 | D87: 46036 | E87: 46050 | G87: 60 | H87: 4.42 | I87: Open
A88: PO-00327 | B88: SKU-0004 | C88: SUP-006 | D88: 46036 | E88: 46041 | F88: 46039 | G88: 50 | H88: 11.55 | I88: Received
A89: PO-00027 | B89: SKU-0058 | C89: SUP-010 | D89: 46037 | E89: 46050 | F89: 46050 | G89: 60 | H89: 6.42 | I89: Received
A90: PO-00141 | B90: SKU-0015 | C90: SUP-007 | D90: 46038 | E90: 46049 | F90: 46053 | G90: 20 | H90: 14.4 | I90: Received
A91: PO-00236 | B91: SKU-0012 | C91: SUP-011 | D91: 46038 | E91: 46048 | F91: 46046 | G91: 50 | H91: 34.53 | I91: Received
A92: PO-00322 | B92: SKU-0055 | C92: SUP-005 | D92: 46041 | E92: 46056 | F92: 46053 | G92: 30 | H92: 4.93 | I92: Received
A93: PO-00248 | B93: SKU-0029 | C93: SUP-012 | D93: 46044 | E93: 46058 | F93: 46058 | G93: 60 | H93: 38 | I93: Received
A94: PO-00255 | B94: SKU-0005 | C94: SUP-006 | D94: 46044 | E94: 46049 | F94: 46048 | G94: 125 | H94: 25.85 | I94: Received
A95: PO-00302 | B95: SKU-0047 | C95: SUP-009 | D95: 46044 | E95: 46048 | F95: 46048 | G95: 50 | H95: 21.05 | I95: Received
A96: PO-00079 | B96: SKU-0022 | C96: SUP-007 | D96: 46045 | E96: 46056 | F96: 46056 | G96: 20 | H96: 21.59 | I96: Received
A97: PO-00088 | B97: SKU-0046 | C97: SUP-009 | D97: 46046 | E97: 46050 | F97: 46047 | G97: 40 | H97: 19.49 | I97: Received
A98: PO-00097 | B98: SKU-0039 | C98: SUP-009 | D98: 46046 | E98: 46050 | F98: 46051 | G98: 30 | H98: 5.81 | I98: Received
A99: PO-00183 | B99: SKU-0027 | C99: SUP-012 | D99: 46046 | E99: 46060 | F99: 46060 | G99: 125 | H99: 17.22 | I99: Received
... A118: PO-00012 | B118: SKU-0041 | C118: SUP-004 | D118: 46070 | E118: 46077 | F118: 46084 | G118: 50 | H118: 33.7 | I118: Received
...

Sheet Sales Transactions
A1: Order ID | B1: Order Date | C1: SKU | D1: Quantity | E1: Unit Selling Price | F1: Discount Pct | G1: Shipping Revenue | H1: Sales Channel | I1: Market | J1: Customer Segment | K1: Order Status | L1: Customer ID
A2: ORD-000021 | B2: 45931 | C2: SKU-0015 | D2: 1 | E2: 26.72 | F2: 0.1 | G2: 0 | H2: Retail Store | I2: Wilmington | J2: Consumer | K2: Completed | L2: CUST-1010
A3: ORD-000298 | B3: 45931 | C3: SKU-0054 | D3: 1 | E3: 72.45 | F3: 0 | G3: 6.99 | H3: Online Store | I3: Wilmington | J3: Corporate | K3: Completed | L3: CUST-1289
A4: ORD-000479 | B4: 45931 | C4: SKU-0002 | D4: 3 | E4: 73.18 | F4: 0.1 | G4: 9.99 | H4: Marketplace | I4: Asheville | J4: Small Business | K4: Completed | L4: CUST-1499
A5: ORD-001785 | B5: 45931 | C5: SKU-0030 | D5: 3 | E5: 44.98 | F5: 0 | G5: 4.99 | H5: Retail Store | I5: Asheville | J5: Small Business | K5: Completed | L5: CUST-1336
A6: ORD-001801 | B6: 45931 | C6: SKU-0001 | D6: 1 | E6: 31.13 | F6: 0.15 | G6: 0 | H6: Online Store | I6: Charlotte | J6: Small Business | K6: Completed | L6: CUST-1587
A7: ORD-002080 | B7: 45931 | C7: SKU-0037 | D7: 4 | E7: 25.18 | F7: 0 | G7: 6.99 | H7: Online Store | I7: Greensboro | J7: Consumer | K7: Completed | L7: CUST-1525
A8: ORD-000270 | B8: 45932 | C8: SKU-0029 | D8: 1 | E8: 79.47 | F8: 0 | G8: 0 | H8: Online Store | I8: Wilmington | J8: Small Business | K8: Completed | L8: CUST-1131
A9: ORD-000937 | B9: 45932 | C9: SKU-0019 | D9: 3 | E9: 29.49 | F9: 0 | G9: 0 | H9: Retail Store | I9: Asheville | J9: Consumer | K9: Completed | L9: CUST-1580
A10: ORD-001847 | B10: 45932 | C10: SKU-0034 | D10: 2 | E10: 53.25 | F10: 0.05 | G10: 0 | H10: Retail Store | I10: Greensboro | J10: Small Business | K10: Completed | L10: CUST-1174
A11: ORD-002390 | B11: 45932 | C11: SKU-0008 | D11: 2 | E11: 30.29 | F11: 0.05 | G11: 0 | H11: Online Store | I11: Greensboro | J11: Corporate | K11: Completed | L11: CUST-1497
A12: ORD-002492 | B12: 45932 | C12: SKU-0041 | D12: 1 | E12: 76.3 | F12: 0.15 | G12: 0 | H12: Marketplace | I12: Wilmington | J12: Corporate | K12: Completed | L12: CUST-1530
A13: ORD-001000 | B13: 45933 | C13: SKU-0048 | D13: 3 | E13: 12.2 | F13: 0 | G13: 9.99 | H13: Retail Store | I13: Wilmington | J13: Consumer | K13: Completed | L13: CUST-1069
... A2501: ORD-002407 | B2501: 46295 | C2501: SKU-0043 | D2501: 2 | E2501: 39.21 | F2501: 0 | G2501: 0 | H2501: Online Store | I2501: Wilmington | J2501: Small Business | K2501: Completed | L2501: CUST-1306

Sheet Suppliers
A1: Supplier ID | B1: Supplier Name | C1: Specialty | D1: City | E1: State | F1: Lead Time Days | G1: On-Time Delivery Rate | H1: Minimum Order Value | I1: Payment Terms
A2: SUP-001 | B2: Piedmont Home Goods | C2: Home & Kitchen | D2: Charlotte | E2: NC | F2: 6 | G2: 0.96 | H2: 150 | I2: Net 30
A3: SUP-002 | B3: Blue Ridge Electronics | C3: Electronics | D3: Asheville | E3: NC | F3: 12 | G3: 0.9 | H3: 350 | I3: Net 30
A4: SUP-003 | B4: Summit Activewear | C4: Fitness | D4: Greenville | E4: SC | F4: 9 | G4: 0.93 | H4: 200 | I4: Net 45
A5: SUP-004 | B5: Harbor Office Supply | C5: Office | D5: Norfolk | E5: VA | F5: 7 | G5: 0.97 | H5: 175 | I5: Net 30
A6: SUP-005 | B6: Metro Lifestyle Brands | C6: Accessories | D6: Atlanta | E6: GA | F6: 15 | G6: 0.88 | H6: 300 | I6: Net 45
A7: SUP-006 | B7: Carolina Kitchen Co. | C7: Home & Kitchen | D7: Raleigh | E7: NC | F7: 5 | G7: 0.98 | H7: 100 | I7: Net 15
A8: SUP-007 | B8: Digital North Distribution | C8: Electronics | D8: Richmond | E8: VA | F8: 11 | G8: 0.92 | H8: 300 | I8: Net 30
A9: SUP-008 | B9: Peak Performance Supply | C9: Fitness | D9: Knoxville | E9: TN | F9: 8 | G9: 0.94 | H9: 200 | I9: Net 30
A10: SUP-009 | B10: PaperTrail Wholesale | C10: Office | D10: Columbia | E10: SC | F10: 4 | G10: 0.97 | H10: 125 | I10: Net 15
A11: SUP-010 | B11: Urban Carry Co. | C11: Accessories | D11: Nashville | E11: TN | F11: 13 | G11: 0.89 | H11: 250 | I11: Net 30
A12: SUP-011 | B12: Coastal Essentials | C12: Home & Kitchen | D12: Wilmington | E12: NC | F12: 10 | G12: 0.91 | H12: 225 | I12: Net 30
A13: SUP-012 | B13: Flex Gear Partners | C13: Fitness | D13: Roanoke | E13: VA | F13: 14 | G13: 0.87 | H13: 325 | I13: Net 45

Sheet Products
A1: SKU | B1: Product Name | C1: Category | D1: Preferred Supplier ID | E1: Unit Cost | F1: List Price | G1: Product Status | H1: Added Date
A2: SKU-0001 | B2: Ceramic Dinnerware Set | C2: Home & Kitchen | D2: SUP-006 | E2: 13.79 | F2: 31.13 | G2: Active | H2: 45364
A3: SKU-0002 | B3: Insulated Water Bottle | C3: Home & Kitchen | D3: SUP-001 | E3: 37 | F3: 73.18 | G3: Active | H3: 45781
A4: SKU-0003 | B4: Nonstick Skillet | C4: Home & Kitchen | D4: SUP-011 | E4: 6.46 | F4: 11.23 | G4: Active | H4: 45918
A5: SKU-0004 | B5: Bamboo Cutting Board | C5: Home & Kitchen | D5: SUP-006 | E5: 11.55 | F5: 23.84 | G5: Active | H5: 45949
A6: SKU-0005 | B6: Glass Food Containers | C6: Home & Kitchen | D6: SUP-006 | E6: 25.85 | F6: 55.2 | G6: Active | H6: 45717
A7: SKU-0006 | B7: Kitchen Scale | C7: Home & Kitchen | D7: SUP-001 | E7: 21.34 | F7: 47.77 | G7: Active | H7: 45494
A8: SKU-0007 | B8: Cotton Bath Towels | C8: Home & Kitchen | D8: SUP-001 | E8: 7.24 | F8: 12.76 | G8: Active | H8: 45403
A9: SKU-0008 | B9: LED Desk Lamp | C9: Home & Kitchen | D9: SUP-001 | E9: 13.1 | F9: 30.29 | G9: Active | H9: 45541
A10: SKU-0009 | B10: Storage Bin Set | C10: Home & Kitchen | D10: SUP-001 | E10: 36.44 | F10: 79.31 | G10: Active | H10: 45522
A11: SKU-0010 | B11: Throw Blanket | C11: Home & Kitchen | D11: SUP-011 | E11: 8.53 | F11: 20.7 | G11: Active | H11: 45932
A12: SKU-0011 | B12: French Press | C12: Home & Kitchen | D12: SUP-011 | E12: 24.06 | F12: 49.34 | G12: Active | H12: 45553
A13: SKU-0012 | B13: Portable Blender | C13: Home & Kitchen | D13: SUP-011 | E13: 34.53 | F13: 81.14 | G13: Discontinued | H13: 45853
... A61: SKU-0060 | B61: Luggage Tag Set | C61: Accessories | D61: SUP-010 | E61: 31.07 | F61: 54.93 | G61: Active | H61: 45298

Sheet Inventory Snapshot
A1: SKU | B1: On-Hand Units | C1: Safety Stock Units | D1: Target Stock Units | E1: Est. Daily Demand | F1: Snapshot Date | G1: On-Order Units | H1: Reserved Units
A2: SKU-0001 | B2: 92 | C2: 33 | D2: 130 | E2: 1.54 | F2: 46295 | G2: 24 | H2: 7
A3: SKU-0002 | B3: 162 | C3: 20 | D3: 177 | E3: 2.72 | F3: 46295 | G3: 24 | H3: 1
A4: SKU-0003 | B4: 180 | C4: 22 | D4: 140 | E4: 0.48 | F4: 46295 | G4: 1 | H4: 8
A5: SKU-0004 | B5: 213 | C5: 35 | D5: 82 | E5: 2.04 | F5: 46295 | G5: 21 | H5: 9
A6: SKU-0005 | B6: 33 | C6: 22 | D6: 175 | E6: 1.28 | F6: 46295 | G6: 20 | H6: 8
A7: SKU-0006 | B7: 153 | C7: 23 | D7: 190 | E7: 1.13 | F7: 46295 | G7: 9 | H7: 5
A8: SKU-0007 | B8: 21 | C8: 31 | D8: 132 | E8: 3.29 | F8: 46295 | G8: 8 | H8: 0
A9: SKU-0008 | B9: 142 | C9: 28 | D9: 223 | E9: 2.42 | F9: 46295 | G9: 7 | H9: 6
A10: SKU-0009 | B10: 71 | C10: 28 | D10: 209 | E10: 0.4 | F10: 46295 | G10: 24 | H10: 6
A11: SKU-0010 | B11: 8 | C11: 14 | D11: 149 | E11: 0.79 | F11: 46295 | G11: 19 | H11: 9
A12: SKU-0011 | B12: 122 | C12: 24 | D12: 161 | E12: 1.87 | F12: 46295 | G12: 6 | H12: 7
A13: SKU-0012 | B13: 188 | C13: 22 | D13: 116 | E13: 3.19 | F13: 46295 | G13: 3 | H13: 3
... A61: SKU-0060 | B61: 151 | C61: 32 | D61: 127 | E61: 1.32 | F61: 46295 | G61: 13 | H61: 6

Sheet SuppliersTableCleaned
A1: Supplier ID | B1: Supplier Name | C1: Specialty | D1: City | E1: State | F1: Lead Time Days | G1: On-Time Delivery Rate | H1: Minimum Order Value | I1: Payment Terms
A2: SUP-001 | B2: Piedmont Home Goods | C2: Home & Kitchen | D2: Charlotte | E2: NC | F2: 6 | G2: 0.96 | H2: 150 | I2: Net 30
A3: SUP-002 | B3: Blue Ridge Electronics | C3: Electronics | D3: Asheville | E3: NC | F3: 12 | G3: 0.9 | H3: 350 | I3: Net 30
A4: SUP-003 | B4: Summit Activewear | C4: Fitness | D4: Greenville | E4: SC | F4: 9 | G4: 0.93 | H4: 200 | I4: Net 45
A5: SUP-004 | B5: Harbor Office Supply | C5: Office | D5: Norfolk | E5: VA | F5: 7 | G5: 0.97 | H5: 175 | I5: Net 30
A6: SUP-005 | B6: Metro Lifestyle Brands | C6: Accessories | D6: Atlanta | E6: GA | F6: 15 | G6: 0.88 | H6: 300 | I6: Net 45
A7: SUP-006 | B7: Carolina Kitchen Co. | C7: Home & Kitchen | D7: Raleigh | E7: NC | F7: 5 | G7: 0.98 | H7: 100 | I7: Net 15
A8: SUP-007 | B8: Digital North Distribution | C8: Electronics | D8: Richmond | E8: VA | F8: 11 | G8: 0.92 | H8: 300 | I8: Net 30
A9: SUP-008 | B9: Peak Performance Supply | C9: Fitness | D9: Knoxville | E9: TN | F9: 8 | G9: 0.94 | H9: 200 | I9: Net 30
A10: SUP-009 | B10: PaperTrail Wholesale | C10: Office | D10: Columbia | E10: SC | F10: 4 | G10: 0.97 | H10: 125 | I10: Net 15
A11: SUP-010 | B11: Urban Carry Co. | C11: Accessories | D11: Nashville | E11: TN | F11: 13 | G11: 0.89 | H11: 250 | I11: Net 30
A12: SUP-011 | B12: Coastal Essentials | C12: Home & Kitchen | D12: Wilmington | E12: NC | F12: 10 | G12: 0.91 | H12: 225 | I12: Net 30
A13: SUP-012 | B13: Flex Gear Partners | C13: Fitness | D13: Roanoke | E13: VA | F13: 14 | G13: 0.87 | H13: 325 | I13: Net 45

Sheet ProductsTableCleaned
A1: SKU | B1: Product Name | C1: Category | D1: Preferred Supplier ID | E1: Unit Cost | F1: List Price | G1: Product Status | H1: Added Date
A2: SKU-0001 | B2: Ceramic Dinnerware Set | C2: Home & Kitchen | D2: SUP-006 | E2: 13.79 | F2: 31.13 | G2: Active | H2: 45364
A3: SKU-0002 | B3: Insulated Water Bottle | C3: Home & Kitchen | D3: SUP-001 | E3: 37 | F3: 73.18 | G3: Active | H3: 45781
A4: SKU-0003 | B4: Nonstick Skillet | C4: Home & Kitchen | D4: SUP-011 | E4: 6.46 | F4: 11.23 | G4: Active | H4: 45918
A5: SKU-0004 | B5: Bamboo Cutting Board | C5: Home & Kitchen | D5: SUP-006 | E5: 11.55 | F5: 23.84 | G5: Active | H5: 45949
A6: SKU-0005 | B6: Glass Food Containers | C6: Home & Kitchen | D6: SUP-006 | E6: 25.85 | F6: 55.2 | G6: Active | H6: 45717
A7: SKU-0006 | B7: Kitchen Scale | C7: Home & Kitchen | D7: SUP-001 | E7: 21.34 | F7: 47.77 | G7: Active | H7: 45494
A8: SKU-0007 | B8: Cotton Bath Towels | C8: Home & Kitchen | D8: SUP-001 | E8: 7.24 | F8: 12.76 | G8: Active | H8: 45403
A9: SKU-0008 | B9: LED Desk Lamp | C9: Home & Kitchen | D9: SUP-001 | E9: 13.1 | F9: 30.29 | G9: Active | H9: 45541
A10: SKU-0009 | B10: Storage Bin Set | C10: Home & Kitchen | D10: SUP-001 | E10: 36.44 | F10: 79.31 | G10: Active | H10: 45522
A11: SKU-0010 | B11: Throw Blanket | C11: Home & Kitchen | D11: SUP-011 | E11: 8.53 | F11: 20.7 | G11: Active | H11: 45932
A12: SKU-0011 | B12: French Press | C12: Home & Kitchen | D12: SUP-011 | E12: 24.06 | F12: 49.34 | G12: Active | H12: 45553
A13: SKU-0012 | B13: Portable Blender | C13: Home & Kitchen | D13: SUP-011 | E13: 34.53 | F13: 81.14 | G13: Discontinued | H13: 45853
... A61: SKU-0060 | B61: Luggage Tag Set | C61: Accessories | D61: SUP-010 | E61: 31.07 | F61: 54.93 | G61: Active | H61: 45298

Sheet SalesTableCleaned
A1: Order ID | B1: Order Date | C1: SKU | D1: Quantity | E1: Unit Selling Price | F1: Discount Pct | G1: Shipping Revenue | H1: Sales Channel | I1: Market | J1: Customer Segment | K1: Order Status | L1: Customer ID
A2: ORD-000021 | B2: 45931 | C2: SKU-0015 | D2: 1 | E2: 26.72 | F2: 0.1 | G2: 0 | H2: Retail Store | I2: Wilmington | J2: Consumer | K2: Completed | L2: CUST-1010
A3: ORD-000298 | B3: 45931 | C3: SKU-0054 | D3: 1 | E3: 72.45 | F3: 0 | G3: 6.99 | H3: Online Store | I3: Wilmington | J3: Corporate | K3: Completed | L3: CUST-1289
A4: ORD-000479 | B4: 45931 | C4: SKU-0002 | D4: 3 | E4: 73.18 | F4: 0.1 | G4: 9.99 | H4: Marketplace | I4: Asheville | J4: Small Business | K4: Completed | L4: CUST-1499
A5: ORD-001785 | B5: 45931 | C5: SKU-0030 | D5: 3 | E5: 44.98 | F5: 0 | G5: 4.99 | H5: Retail Store | I5: Asheville | J5: Small Business | K5: Completed | L5: CUST-1336
A6: ORD-001801 | B6: 45931 | C6: SKU-0001 | D6: 1 | E6: 31.13 | F6: 0.15 | G6: 0 | H6: Online Store | I6: Charlotte | J6: Small Business | K6: Completed | L6: CUST-1587
A7: ORD-002080 | B7: 45931 | C7: SKU-0037 | D7: 4 | E7: 25.18 | F7: 0 | G7: 6.99 | H7: Online Store | I7: Greensboro | J7: Consumer | K7: Completed | L7: CUST-1525
A8: ORD-000270 | B8: 45932 | C8: SKU-0029 | D8: 1 | E8: 79.47 | F8: 0 | G8: 0 | H8: Online Store | I8: Wilmington | J8: Small Business | K8: Completed | L8: CUST-1131
A9: ORD-000937 | B9: 45932 | C9: SKU-0019 | D9: 3 | E9: 29.49 | F9: 0 | G9: 0 | H9: Retail Store | I9: Asheville | J9: Consumer | K9: Completed | L9: CUST-1580
A10: ORD-001847 | B10: 45932 | C10: SKU-0034 | D10: 2 | E10: 53.25 | F10: 0.05 | G10: 0 | H10: Retail Store | I10: Greensboro | J10: Small Business | K10: Completed | L10: CUST-1174
A11: ORD-002390 | B11: 45932 | C11: SKU-0008 | D11: 2 | E11: 30.29 | F11: 0.05 | G11: 0 | H11: Online Store | I11: Greensboro | J11: Corporate | K11: Completed | L11: CUST-1497
A12: ORD-002492 | B12: 45932 | C12: SKU-0041 | D12: 1 | E12: 76.3 | F12: 0.15 | G12: 0 | H12: Marketplace | I12: Wilmington | J12: Corporate | K12: Completed | L12: CUST-1530
A13: ORD-001000 | B13: 45933 | C13: SKU-0048 | D13: 3 | E13: 12.2 | F13: 0 | G13: 9.99 | H13: Retail Store | I13: Wilmington | J13: Consumer | K13: Completed | L13: CUST-1069
... A2501: ORD-002407 | B2501: 46295 | C2501: SKU-0043 | D2501: 2 | E2501: 39.21 | F2501: 0 | G2501: 0 | H2501: Online Store | I2501: Wilmington | J2501: Small Business | K2501: Completed | L2501: CUST-1306

Sheet PurchaseOrdersCleaned
A1: PO ID | B1: SKU | C1: Supplier ID | D1: Order Date | E1: Expected Date | F1: Actual Delivery Date | G1: Units Ordered | H1: Unit Purchase Cost | I1: PO Status
A2: PO-00258 | B2: SKU-0005 | C2: SUP-006 | D2: 45932 | E2: 45937 | F2: 45935 | G2: 125 | H2: 25.85 | I2: Received
A3: PO-00220 | B3: SKU-0009 | C3: SUP-001 | D3: 45933 | E3: 45939 | F3: 45939 | G3: 40 | H3: 36.44 | I3: Received
A4: PO-00317 | B4: SKU-0013 | C4: SUP-002 | D4: 45933 | E4: 45945 | F4: 45945 | G4: 75 | H4: 21.33 | I4: Received
A5: PO-00107 | B5: SKU-0007 | C5: SUP-001 | D5: 45934 | E5: 45940 | F5: 45940 | G5: 60 | H5: 7.24 | I5: Received
A6: PO-00205 | B6: SKU-0038 | C6: SUP-004 | D6: 45942 | E6: 45949 | F6: 45947 | G6: 60 | H6: 41.96 | I6: Received
A7: PO-00312 | B7: SKU-0054 | C7: SUP-005 | D7: 45942 | E7: 45957 | F7: 45957 | G7: 100 | H7: 30.61 | I7: Received
A8: PO-00147 | B8: SKU-0003 | C8: SUP-011 | D8: 45943 | E8: 45953 | F8: 45953 | G8: 75 | H8: 6.46 | I8: Received
A9: PO-00001 | B9: SKU-0024 | C9: SUP-002 | D9: 45946 | E9: 45958 | G9: 100 | H9: 40.34 | I9: Cancelled
A10: PO-00044 | B10: SKU-0037 | C10: SUP-009 | D10: 45949 | E10: 45953 | F10: 45954 | G10: 125 | H10: 13.85 | I10: Received
A11: PO-00185 | B11: SKU-0046 | C11: SUP-009 | D11: 45949 | E11: 45953 | F11: 45953 | G11: 30 | H11: 19.49 | I11: Received
A12: PO-00264 | B12: SKU-0055 | C12: SUP-005 | D12: 45950 | E12: 45965 | F12: 45972 | G12: 50 | H12: 4.93 | I12: Received
A13: PO-00057 | B13: SKU-0020 | C13: SUP-002 | D13: 45952 | E13: 45964 | F13: 45964 | G13: 40 | H13: 43.46 | I13: Received
A14: PO-00095 | B14: SKU-0018 | C14: SUP-002 | D14: 45952 | E14: 45964 | F14: 45964 | G14: 40 | H14: 7.75 | I14: Received
A15: PO-00269 | B15: SKU-0060 | C15: SUP-010 | D15: 45957 | E15: 45970 | F15: 45971 | G15: 75 | H15: 31.07 | I15: Received
A16: PO-00179 | B16: SKU-0033 | C16: SUP-003 | D16: 45958 | E16: 45967 | F16: 45967 | G16: 50 | H16: 45 | I16: Received
A17: PO-00278 | B17: SKU-0054 | C17: SUP-005 | D17: 45960 | E17: 45975 | F17: 45975 | G17: 60 | H17: 30.61 | I17: Received
A18: PO-00280 | B18: SKU-0007 | C18: SUP-001 | D18: 45963 | E18: 45969 | F18: 45969 | G18: 30 | H18: 7.24 | I18: Received
A19: PO-00026 | B19: SKU-0027 | C19: SUP-012 | D19: 45964 | E19: 45978 | F19: 45978 | G19: 40 | H19: 17.22 | I19: Received
A20: PO-00098 | B20: SKU-0011 | C20: SUP-011 | D20: 45966 | E20: 45976 | F20: 45976 | G20: 30 | H20: 24.06 | I20: Received
A21: PO-00330 | B21: SKU-0046 | C21: SUP-009 | D21: 45967 | E21: 45971 | F21: 45972 | G21: 30 | H21: 19.49 | I21: Received
A22: PO-00140 | B22: SKU-0042 | C22: SUP-004 | D22: 45968 | E22: 45975 | G22: 60 | H22: 28.8 | I22: Open
A23: PO-00178 | B23: SKU-0012 | C23: SUP-011 | D23: 45968 | E23: 45978 | F23: 45979 | G23: 100 | H23: 34.53 | I23: Received
A24: PO-00209 | B24: SKU-0042 | C24: SUP-004 | D24: 45968 | E24: 45975 | F24: 45977 | G24: 30 | H24: 28.8 | I24: Received
A25: PO-00043 | B25: SKU-0018 | C25: SUP-002 | D25: 45969 | E25: 45981 | G25: 60 | H25: 7.75 | I25: Open
A26: PO-00283 | B26: SKU-0038 | C26: SUP-004 | D26: 45969 | E26: 45976 | G26: 125 | H26: 41.96 | I26: Open
A27: PO-00091 | B27: SKU-0010 | C27: SUP-011 | D27: 45970 | E27: 45980 | G27: 100 | H27: 8.53 | I27: Cancelled
A28: PO-00033 | B28: SKU-0056 | C28: SUP-010 | D28: 45971 | E28: 45984 | G28: 20 | H28: 44.67 | I28: Open
A29: PO-00102 | B29: SKU-0047 | C29: SUP-009 | D29: 45972 | E29: 45976 | F29: 45976 | G29: 100 | H29: 21.05 | I29: Received
A30: PO-00251 | B30: SKU-0004 | C30: SUP-006 | D30: 45973 | E30: 45978 | G30: 50 | H30: 11.55 | I30: Open
A31: PO-00016 | B31: SKU-0059 | C31: SUP-005 | D31: 45974 | E31: 45989 | F31: 45987 | G31: 100 | H31: 18.04 | I31: Received
A32: PO-00047 | B32: SKU-0007 | C32: SUP-001 | D32: 45974 | E32: 45980 | F32: 45979 | G32: 75 | H32: 7.24 | I32: Received
A33: PO-00247 | B33: SKU-0030 | C33: SUP-003 | D33: 45975 | E33: 45984 | F33: 45984 | G33: 50 | H33: 23.48 | I33: Received
A34: PO-00198 | B34: SKU-0018 | C34: SUP-002 | D34: 45976 | E34: 45988 | F34: 45989 | G34: 40 | H34: 7.75 | I34: Received
A35: PO-00243 | B35: SKU-0005 | C35: SUP-006 | D35: 45980 | E35: 45985 | G35: 75 | H35: 25.85 | I35: Open
A36: PO-00325 | B36: SKU-0006 | C36: SUP-001 | D36: 45981 | E36: 45987 | G36: 75 | H36: 21.34 | I36: Cancelled
A37: PO-00201 | B37: SKU-0043 | C37: SUP-004 | D37: 45983 | E37: 45990 | F37: 45997 | G37: 60 | H37: 19.66 | I37: Received
A38: PO-00090 | B38: SKU-0032 | C38: SUP-012 | D38: 45984 | E38: 45998 | F38: 45999 | G38: 75 | H38: 4.42 | I38: Received
A39: PO-00041 | B39: SKU-0028 | C39: SUP-008 | D39: 45985 | E39: 45993 | F39: 45995 | G39: 20 | H39: 17.55 | I39: Received
A40: PO-00117 | B40: SKU-0011 | C40: SUP-011 | D40: 45985 | E40: 45995 | F40: 45997 | G40: 75 | H40: 24.06 | I40: Received
A41: PO-00169 | B41: SKU-0037 | C41: SUP-009 | D41: 45986 | E41: 45990 | F41: 45990 | G41: 50 | H41: 13.85 | I41: Received
A42: PO-00250 | B42: SKU-0023 | C42: SUP-007 | D42: 45986 | E42: 45997 | F42: 45996 | G42: 30 | H42: 23.26 | I42: Received
A43: PO-00017 | B43: SKU-0044 | C43: SUP-009 | D43: 45988 | E43: 45992 | F43: 45991 | G43: 125 | H43: 41.46 | I43: Received
A44: PO-00298 | B44: SKU-0022 | C44: SUP-007 | D44: 45989 | E44: 46000 | F44: 46000 | G44: 100 | H44: 21.59 | I44: Received
A45: PO-00153 | B45: SKU-0052 | C45: SUP-005 | D45: 45991 | E45: 46006 | F45: 46007 | G45: 125 | H45: 18.73 | I45: Received
A46: PO-00080 | B46: SKU-0051 | C46: SUP-010 | D46: 45992 | E46: 46005 | G46: 100 | H46: 23.03 | I46: Open
A47: PO-00288 | B47: SKU-0030 | C47: SUP-003 | D47: 45992 | E47: 46001 | F47: 46005 | G47: 100 | H47: 23.48 | I47: Received
A48: PO-00304 | B48: SKU-0054 | C48: SUP-005 | D48: 45993 | E48: 46008 | F48: 46008 | G48: 40 | H48: 30.61 | I48: Received
A49: PO-00268 | B49: SKU-0006 | C49: SUP-001 | D49: 45994 | E49: 46000 | F49: 46000 | G49: 20 | H49: 21.34 | I49: Received
A50: PO-00019 | B50: SKU-0007 | C50: SUP-001 | D50: 45995 | E50: 46001 | F50: 46003 | G50: 60 | H50: 7.24 | I50: Received
A51: PO-00287 | B51: SKU-0028 | C51: SUP-008 | D51: 45995 | E51: 46003 | G51: 75 | H51: 17.55 | I51: Open
A52: PO-00199 | B52: SKU-0049 | C52: SUP-010 | D52: 45996 | E52: 46009 | G52: 60 | H52: 39.76 | I52: Open
A53: PO-00204 | B53: SKU-0031 | C53: SUP-012 | D53: 45997 | E53: 46011 | F53: 46011 | G53: 40 | H53: 36.28 | I53: Received
A54: PO-00006 | B54: SKU-0025 | C54: SUP-003 | D54: 45998 | E54: 46007 | G54: 125 | H54: 13.41 | I54: Open
A55: PO-00232 | B55: SKU-0005 | C55: SUP-006 | D55: 46000 | E55: 46005 | F55: 46009 | G55: 125 | H55: 25.85 | I55: Received
A56: PO-00323 | B56: SKU-0036 | C56: SUP-003 | D56: 46000 | E56: 46009 | F56: 46010 | G56: 60 | H56: 37.14 | I56: Received
A57: PO-00200 | B57: SKU-0023 | C57: SUP-007 | D57: 46001 | E57: 46012 | G57: 75 | H57: 23.26 | I57: Open
A58: PO-00194 | B58: SKU-0034 | C58: SUP-008 | D58: 46002 | E58: 46010 | F58: 46009 | G58: 60 | H58: 22.11 | I58: Received
A59: PO-00120 | B59: SKU-0055 | C59: SUP-005 | D59: 46004 | E59: 46019 | F59: 46019 | G59: 75 | H59: 4.93 | I59: Received
A60: PO-00106 | B60: SKU-0023 | C60: SUP-007 | D60: 46005 | E60: 46016 | F60: 46020 | G60: 100 | H60: 23.26 | I60: Received
A61: PO-00244 | B61: SKU-0032 | C61: SUP-012 | D61: 46006 | E61: 46020 | F61: 46020 | G61: 60 | H61: 4.42 | I61: Received
A62: PO-00129 | B62: SKU-0057 | C62: SUP-010 | D62: 46009 | E62: 46022 | F62: 46023 | G62: 60 | H62: 25.69 | I62: Received
A63: PO-00020 | B63: SKU-0038 | C63: SUP-004 | D63: 46010 | E63: 46017 | F63: 46016 | G63: 30 | H63: 41.96 | I63: Received
A64: PO-00075 | B64: SKU-0049 | C64: SUP-010 | D64: 46010 | E64: 46023 | F64: 46024 | G64: 40 | H64: 39.76 | I64: Received
A65: PO-00217 | B65: SKU-0031 | C65: SUP-012 | D65: 46011 | E65: 46025 | F65: 46026 | G65: 20 | H65: 36.28 | I65: Received
A66: PO-00122 | B66: SKU-0021 | C66: SUP-002 | D66: 46014 | E66: 46026 | F66: 46027 | G66: 20 | H66: 13.98 | I66: Received
A67: PO-00051 | B67: SKU-0044 | C67: SUP-009 | D67: 46015 | E67: 46019 | F67: 46023 | G67: 100 | H67: 41.46 | I67: Received
A68: PO-00159 | B68: SKU-0023 | C68: SUP-007 | D68: 46016 | E68: 46027 | F68: 46025 | G68: 125 | H68: 23.26 | I68: Received
A69: PO-00265 | B69: SKU-0028 | C69: SUP-008 | D69: 46017 | E69: 46025 | G69: 60 | H69: 17.55 | I69: Open
A70: PO-00321 | B70: SKU-0005 | C70: SUP-006 | D70: 46017 | E70: 46022 | F70: 46022 | G70: 40 | H70: 25.85 | I70: Received
A71: PO-00231 | B71: SKU-0047 | C71: SUP-009 | D71: 46018 | E71: 46022 | F71: 46022 | G71: 20 | H71: 21.05 | I71: Received
A72: PO-00138 | B72: SKU-0032 | C72: SUP-012 | D72: 46019 | E72: 46033 | F72: 46037 | G72: 100 | H72: 4.42 | I72: Received
A73: PO-00246 | B73: SKU-0057 | C73: SUP-010 | D73: 46020 | E73: 46033 | F73: 46033 | G73: 100 | H73: 25.69 | I73: Received
A74: PO-00166 | B74: SKU-0043 | C74: SUP-004 | D74: 46023 | E74: 46030 | F74: 46031 | G74: 40 | H74: 19.66 | I74: Received
A75: PO-00163 | B75: SKU-0056 | C75: SUP-010 | D75: 46024 | E75: 46037 | F75: 46035 | G75: 100 | H75: 44.67 | I75: Received
A76: PO-00052 | B76: SKU-0017 | C76: SUP-002 | D76: 46025 | E76: 46037 | F76: 46036 | G76: 40 | H76: 31.21 | I76: Received
A77: PO-00110 | B77: SKU-0027 | C77: SUP-012 | D77: 46025 | E77: 46039 | F77: 46040 | G77: 100 | H77: 17.22 | I77: Received
A78: PO-00242 | B78: SKU-0043 | C78: SUP-004 | D78: 46025 | E78: 46032 | G78: 50 | H78: 19.66 | I78: Open
A79: PO-00124 | B79: SKU-0031 | C79: SUP-012 | D79: 46027 | E79: 46041 | G79: 50 | H79: 36.28 | I79: Open
A80: PO-00058 | B80: SKU-0002 | C80: SUP-001 | D80: 46028 | E80: 46034 | F80: 46038 | G80: 100 | H80: 37 | I80: Received
A81: PO-00286 | B81: SKU-0040 | C81: SUP-009 | D81: 46028 | E81: 46032 | F81: 46034 | G81: 50 | H81: 17.33 | I81: Received
A82: PO-00131 | B82: SKU-0050 | C82: SUP-010 | D82: 46030 | E82: 46043 | F82: 46050 | G82: 50 | H82: 18.54 | I82: Received
A83: PO-00086 | B83: SKU-0042 | C83: SUP-004 | D83: 46031 | E83: 46038 | F83: 46037 | G83: 100 | H83: 28.8 | I83: Received
A84: PO-00245 | B84: SKU-0012 | C84: SUP-011 | D84: 46032 | E84: 46042 | F84: 46039 | G84: 40 | H84: 34.53 | I84: Received
A85: PO-00038 | B85: SKU-0017 | C85: SUP-002 | D85: 46034 | E85: 46046 | F85: 46050 | G85: 50 | H85: 31.21 | I85: Received
A86: PO-00096 | B86: SKU-0053 | C86: SUP-010 | D86: 46034 | E86: 46047 | F86: 46047 | G86: 50 | H86: 44.56 | I86: Received
A87: PO-00060 | B87: SKU-0032 | C87: SUP-012 | D87: 46036 | E87: 46050 | G87: 60 | H87: 4.42 | I87: Open
A88: PO-00327 | B88: SKU-0004 | C88: SUP-006 | D88: 46036 | E88: 46041 | F88: 46039 | G88: 50 | H88: 11.55 | I88: Received
A89: PO-00027 | B89: SKU-0058 | C89: SUP-010 | D89: 46037 | E89: 46050 | F89: 46050 | G89: 60 | H89: 6.42 | I89: Received
A90: PO-00141 | B90: SKU-0015 | C90: SUP-007 | D90: 46038 | E90: 46049 | F90: 46053 | G90: 20 | H90: 14.4 | I90: Received
A91: PO-00236 | B91: SKU-0012 | C91: SUP-011 | D91: 46038 | E91: 46048 | F91: 46046 | G91: 50 | H91: 34.53 | I91: Received
A92: PO-00322 | B92: SKU-0055 | C92: SUP-005 | D92: 46041 | E92: 46056 | F92: 46053 | G92: 30 | H92: 4.93 | I92: Received
A93: PO-00248 | B93: SKU-0029 | C93: SUP-012 | D93: 46044 | E93: 46058 | F93: 46058 | G93: 60 | H93: 38 | I93: Received
A94: PO-00255 | B94: SKU-0005 | C94: SUP-006 | D94: 46044 | E94: 46049 | F94: 46048 | G94: 125 | H94: 25.85 | I94: Received
A95: PO-00302 | B95: SKU-0047 | C95: SUP-009 | D95: 46044 | E95: 46048 | F95: 46048 | G95: 50 | H95: 21.05 | I95: Received
A96: PO-00079 | B96: SKU-0022 | C96: SUP-007 | D96: 46045 | E96: 46056 | F96: 46056 | G96: 20 | H96: 21.59 | I96: Received
A97: PO-00088 | B97: SKU-0046 | C97: SUP-009 | D97: 46046 | E97: 46050 | F97: 46047 | G97: 40 | H97: 19.49 | I97: Received
A98: PO-00097 | B98: SKU-0039 | C98: SUP-009 | D98: 46046 | E98: 46050 | F98: 46051 | G98: 30 | H98: 5.81 | I98: Received
A99: PO-00183 | B99: SKU-0027 | C99: SUP-012 | D99: 46046 | E99: 46060 | F99: 46060 | G99: 125 | H99: 17.22 | I99: Received
... A118: PO-00012 | B118: SKU-0041 | C118: SUP-004 | D118: 46070 | E118: 46077 | F118: 46084 | G118: 50 | H118: 33.7 | I118: Received
...

Sheet InventorySnapShotCleaned
A1: SKU | B1: On-Hand Units | C1: Safety Stock Units | D1: Target Stock Units | E1: Est. Daily Demand | F1: Snapshot Date | G1: On-Order Units | H1: Reserved Units
A2: SKU-0001 | B2: 92 | C2: 33 | D2: 130 | E2: 1.54 | F2: 46295 | G2: 24 | H2: 7
A3: SKU-0002 | B3: 162 | C3: 20 | D3: 177 | E3: 2.72 | F3: 46295 | G3: 24 | H3: 1
A4: SKU-0003 | B4: 180 | C4: 22 | D4: 140 | E4: 0.48 | F4: 46295 | G4: 1 | H4: 8
A5: SKU-0004 | B5: 213 | C5: 35 | D5: 82 | E5: 2.04 | F5: 46295 | G5: 21 | H5: 9
A6: SKU-0005 | B6: 33 | C6: 22 | D6: 175 | E6: 1.28 | F6: 46295 | G6: 20 | H6: 8
A7: SKU-0006 | B7: 153 | C7: 23 | D7: 190 | E7: 1.13 | F7: 46295 | G7: 9 | H7: 5
A8: SKU-0007 | B8: 21 | C8: 31 | D8: 132 | E8: 3.29 | F8: 46295 | G8: 8 | H8: 0
A9: SKU-0008 | B9: 142 | C9: 28 | D9: 223 | E9: 2.42 | F9: 46295 | G9: 7 | H9: 6
A10: SKU-0009 | B10: 71 | C10: 28 | D10: 209 | E10: 0.4 | F10: 46295 | G10: 24 | H10: 6
A11: SKU-0010 | B11: 8 | C11: 14 | D11: 149 | E11: 0.79 | F11: 46295 | G11: 19 | H11: 9
A12: SKU-0011 | B12: 122 | C12: 24 | D12: 161 | E12: 1.87 | F12: 46295 | G12: 6 | H12: 7
A13: SKU-0012 | B13: 188 | C13: 22 | D13: 116 | E13: 3.19 | F13: 46295 | G13: 3 | H13: 3
... A61: SKU-0060 | B61: 151 | C61: 32 | D61: 127 | E61: 1.32 | F61: 46295 | G61: 13 | H61: 6

Sheet Sales_Analysis
A1: Order ID | B1: Order Date | C1: SKU | D1: Quantity | E1: Unit Selling Price | F1: Discount Pct | G1: Shipping Revenue | H1: Sales Channel | I1: Market | J1: Customer Segment | K1: Order Status | L1: Customer ID | M1: Product Name | N1: Category | O1: Unit Cost | P1: List Price | Q1: Gross Sales | R1: Discount Amount | S1: Net Sales | T1: Cost Of Good Sold | U1: Gross Profit | V1: Recognized Revenue | W1: Recognized Gross Profit
A2: ORD-000021 | B2: 45931 | C2: SKU-0015 | D2: 1 | E2: 26.72 | F2: 0.1 | G2: 0 | H2: Retail Store | I2: Wilmington | J2: Consumer | K2: Completed | L2: CUST-1010 | M2: Bluetooth Speaker | N2: Electronics | O2: 14.4 | P2: 26.72 | Q2: =Sales_Analysis[[#This Row],[Quantity]]*Sales_Analysis[[#This Row],[Unit Selling Price]] -> 26.72 | R2: =Sales_Analysis[[#This Row],[Gross Sales ]]*Sales_Analysis[[#This Row],[Discount Pct]] -> 2.672 | S2: =Sales_Analysis[[#This Row],[Gross Sales ]]-Sales_Analysis[[#This Row],[Discount Amount]] -> 24.048 | T2: =Sales_Analysis[[#This Row],[Quantity]]*Sales_Analysis[[#This Row],[Unit Cost]] -> 14.4 | U2: =Sales_Analysis[[#This Row],[Net Sales ]]-Sales_Analysis[[#This Row],[Cost Of Good Sold]] -> 9.648 | V2: =IF(Sales_Analysis[[#This Row],[Order Status]]="Completed",Sales_Analysis[[#This Row],[Net Sales ]],0) -> 24.048 | W2: =IF(Sales_Analysis[[#This Row],[Order Status]]="Completed",Sales_Analysis[[#This Row],[Gross Profit ]],0) -> 9.648
A3: ORD-001900 | B3: 45938 | C3: SKU-0015 | D3: 2 | E3: 26.72 | F3: 0 | G3: 4.99 | H3: Marketplace | I3: Raleigh | J3: Corporate | K3: Completed | L3: CUST-1507 | M3: Bluetooth Speaker | N3: Electronics | O3: 14.4 | P3: 26.72 | Q3: =Sales_Analysis[[#This Row],[Quantity]]*Sales_Analysis[[#This Row],[Unit Selling Price]] -> 53.44 | R3: =Sales_Analysis[[#This Row],[Gross Sales ]]*Sales_Analysis[[#This Row],[Discount Pct]] -> 0 | S3: =Sales_Analysis[[#This Row],[Gross Sales ]]-Sales_Analysis[[#This Row],[Discount Amount]] -> 53.44 | T3: =Sales_Analysis[[#This Row],[Quantity]]*Sales_Analysis[[#This Row],[Unit Cost]] -> 28.8 | U3: =Sales_Analysis[[#This Row],[Net Sales ]]-Sales_Analysis[[#This Row],[Cost Of Good Sold]] -> 24.64 | V3: =IF(Sales_Analysis[[#This Row],[Order Status]]="Completed",Sales_Analysis[[#This Row],[Net Sales ]],0) -> 53.44 | W3: =IF(Sales_Analysis[[#This Row],[Order Status]]="Completed",Sales_Analysis[[#This Row],[Gross Profit ]],0) -> 24.64
A4: ORD-001801 | B4: 45931 | C4: SKU-0001 | D4: 1 | E4: 31.13 | F4: 0.15 | G4: 0 | H4: Online Store | I4: Charlotte | J4: Small Business | K4: Completed | L4: CUST-1587 | M4: Ceramic Dinnerware Set | N4: Home & Kitchen | O4: 13.79 | P4: 31.13 | Q4: =Sales_Analysis[[#This Row],[Quantity]]*Sales_Analysis[[#This Row],[Unit Selling Price]] -> 31.13 | R4: =Sales_Analysis[[#This Row],[Gross Sales ]]*Sales_Analysis[[#This Row],[Discount Pct]] -> 4.6695 | S4: =Sales_Analysis[[#This Row],[Gross Sales ]]-Sales_Analysis[[#This Row],[Discount Amount]] -> 26.4605 | T4: =Sales_Analysis[[#This Row],[Quantity]]*Sales_Analysis[[#This Row],[Unit Cost]] -> 13.79 | U4: =Sales_Analysis[[#This Row],[Net Sales ]]-Sales_Analysis[[#This Row],[Cost Of Good Sold]] -> 12.6705 | V4: =IF(Sales_Analysis[[#This Row],[Order Status]]="Completed",Sales_Analysis[[#This Row],[Net Sales ]],0) -> 26.4605 | W4: =IF(Sales_Analysis[[#This Row],[Order Status]]="Completed",Sales_Analysis[[#This Row],[Gross Profit ]],0) -> 12.6705
A5: ORD-002456 | B5: 45934 | C5: SKU-0001 | D5: 3 | E5: 31.13 | F5: 0.1 | G5: 6.99 | H5: Retail Store | I5: Wilmington | J5: Small Business | K5: Completed | L5: CUST-1182 | M5: Ceramic Dinnerware Set | N5: Home & Kitchen | O5: 13.79 | P5: 31.13 | Q5: =Sales_Analysis[[#This Row],[Quantity]]*Sales_Analysis[[#This Row],[Unit Selling Price]] -> 93.39 | R5: =Sales_Analysis[[#This Row],[Gross Sales ]]*Sales_Analysis[[#This Row],[Discount Pct]] -> 9.339 | S5: =Sales_Analysis[[#This Row],[Gross Sales ]]-Sales_Analysis[[#This Row],[Discount Amount]] -> 84.051 | T5: =Sales_Analysis[[#This Row],[Quantity]]*Sales_Analysis[[#This Row],[Unit Cost]] -> 41.37 | U5: =Sales_Analysis[[#This Row],[Net Sales ]]-Sales_Analysis[[#This Row],[Cost Of Good Sold]] -> 42.681 | V5: =IF(Sales_Analysis[[#This Row],[Order Status]]="Completed",Sales_Analysis[[#This Row],[Net Sales ]],0) -> 84.051 | W5: =IF(Sales_Analysis[[#This Row],[Order Status]]="Completed",Sales_Analysis[[#This Row],[Gross Profit ]],0) -> 42.681
A6: ORD-002245 | B6: 45936 | C6: SKU-0001 | D6: 5 | E6: 31.13 | F6: 0 | G6: 0 | H6: Marketplace | I6: Asheville | J6: Consumer | K6: Completed | L6: CUST-1181 | M6: Ceramic Dinnerware Set | N6: Home & Kitchen | O6: 13.79 | P6: 31.13 | Q6: =Sales_Analysis[[#This Row],[Quantity]]*Sales_Analysis[[#This Row],[Unit Selling Price]] -> 155.65 | R6: =Sales_Analysis[[#This Row],[Gross Sales ]]*Sales_Analysis[[#This Row],[Discount Pct]] -> 0 | S6: =Sales_Analysis[[#This Row],[Gross Sales ]]-Sales_Analysis[[#This Row],[Discount Amount]] -> 155.65 | T6: =Sales_Analysis[[#This Row],[Quantity]]*Sales_Analysis[[#This Row],[Unit Cost]] -> 68.95 | U6: =Sales_Analysis[[#This Row],[Net Sales ]]-Sales_Analysis[[#This Row],[Cost Of Good Sold]] -> 86.7 | V6: =IF(Sales_Analysis[[#This Row],[Order Status]]="Completed",Sales_Analysis[[#This Row],[Net Sales ]],0) -> 155.65 | W6: =IF(Sales_Analysis[[#This Row],[Order Status]]="Completed",Sales_Analysis[[#This Row],[Gross Profit ]],0) -> 86.7
A7: ORD-000298 | B7: 45931 | C7: SKU-0054 | D7: 1 | E7: 72.45 | F7: 0 | G7: 6.99 | H7: Online Store | I7: Wilmington | J7: Corporate | K7: Completed | L7: CUST-1289 | M7: Travel Organizer | N7: Accessories | O7: 30.61 | P7: 72.45 | Q7: =Sales_Analysis[[#This Row],[Quantity]]*Sales_Analysis[[#This Row],[Unit Selling Price]] -> 72.45 | R7: =Sales_Analysis[[#This Row],[Gross Sales ]]*Sales_Analysis[[#This Row],[Discount Pct]] -> 0 | S7: =Sales_Analysis[[#This Row],[Gross Sales ]]-Sales_Analysis[[#This Row],[Discount Amount]] -> 72.45 | T7: =Sales_Analysis[[#This Row],[Quantity]]*Sales_Analysis[[#This Row],[Unit Cost]] -> 30.61 | U7: =Sales_Analysis[[#This Row],[Net Sales ]]-Sales_Analysis[[#This Row],[Cost Of Good Sold]] -> 41.84 | V7: =IF(Sales_Analysis[[#This Row],[Order Status]]="Completed",Sales_Analysis[[#This Row],[Net Sales ]],0) -> 72.45 | W7: =IF(Sales_Analysis[[#This Row],[Order Status]]="Completed",Sales_Analysis[[#This Row],[Gross Profit ]],0) -> 41.84
A8: ORD-000479 | B8: 45931 | C8: SKU-0002 | D8: 3 | E8: 73.18 | F8: 0.1 | G8: 9.99 | H8: Marketplace | I8: Asheville | J8: Small Business | K8: Completed | L8: CUST-1499 | M8: Insulated Water Bottle | N8: Home & Kitchen | O8: 37 | P8: 73.18 | Q8: =Sales_Analysis[[#This Row],[Quantity]]*Sales_Analysis[[#This Row],[Unit Selling Price]] -> 219.54 | R8: =Sales_Analysis[[#This Row],[Gross Sales ]]*Sales_Analysis[[#This Row],[Discount Pct]] -> 21.954 | S8: =Sales_Analysis[[#This Row],[Gross Sales ]]-Sales_Analysis[[#This Row],[Discount Amount]] -> 197.586 | T8: =Sales_Analysis[[#This Row],[Quantity]]*Sales_Analysis[[#This Row],[Unit Cost]] -> 111 | U8: =Sales_Analysis[[#This Row],[Net Sales ]]-Sales_Analysis[[#This Row],[Cost Of Good Sold]] -> 86.586 | V8: =IF(Sales_Analysis[[#This Row],[Order Status]]="Completed",Sales_Analysis[[#This Row],[Net Sales ]],0) -> 197.586 | W8: =IF(Sales_Analysis[[#This Row],[Order Status]]="Completed",Sales_Analysis[[#This Row],[Gross Profit ]],0) -> 86.586
A9: ORD-001785 | B9: 45931 | C9: SKU-0030 | D9: 3 | E9: 44.98 | F9: 0 | G9: 4.99 | H9: Retail Store | I9: Asheville | J9: Small Business | K9: Completed | L9: CUST-1336 | M9: Workout Gloves | N9: Fitness | O9: 23.48 | P9: 44.98 | Q9: =Sales_Analysis[[#This Row],[Quantity]]*Sales_Analysis[[#This Row],[Unit Selling Price]] -> 134.94 | R9: =Sales_Analysis[[#This Row],[Gross Sales ]]*Sales_Analysis[[#This Row],[Discount Pct]] -> 0 | S9: =Sales_Analysis[[#This Row],[Gross Sales ]]-Sales_Analysis[[#This Row],[Discount Amount]] -> 134.94 | T9: =Sales_Analysis[[#This Row],[Quantity]]*Sales_Analysis[[#This Row],[Unit Cost]] -> 70.44 | U9: =Sales_Analysis[[#This Row],[Net Sales ]]-Sales_Analysis[[#This Row],[Cost Of Good Sold]] -> 64.5 | V9: =IF(Sales_Analysis[[#This Row],[Order Status]]="Completed",Sales_Analysis[[#This Row],[Net Sales ]],0) -> 134.94 | W9: =IF(Sales_Analysis[[#This Row],[Order Status]]="Completed",Sales_Analysis[[#This Row],[Gross Profit ]],0) -> 64.5
A10: ORD-001630 | B10: 45938 | C10: SKU-0030 | D10: 1 | E10: 44.98 | F10: 0 | G10: 0 | H10: Online Store | I10: Charlotte | J10: Consumer | K10: Completed | L10: CUST-1468 | M10: Workout Gloves | N10: Fitness | O10: 23.48 | P10: 44.98 | Q10: =Sales_Analysis[[#This Row],[Quantity]]*Sales_Analysis[[#This Row],[Unit Selling Price]] -> 44.98 | R10: =Sales_Analysis[[#This Row],[Gross Sales ]]*Sales_Analysis[[#This Row],[Discount Pct]] -> 0 | S10: =Sales_Analysis[[#This Row],[Gross Sales ]]-Sales_Analysis[[#This Row],[Discount Amount]] -> 44.98 | T10: =Sales_Analysis[[#This Row],[Quantity]]*Sales_Analysis[[#This Row],[Unit Cost]] -> 23.48 | U10: =Sales_Analysis[[#This Row],[Net Sales ]]-Sales_Analysis[[#This Row],[Cost Of Good Sold]] -> 21.5 | V10: =IF(Sales_Analysis[[#This Row],[Order Status]]="Completed",Sales_Analysis[[#This Row],[Net Sales ]],0) -> 44.98 | W10: =IF(Sales_Analysis[[#This Row],[Order Status]]="Completed",Sales_Analysis[[#This Row],[Gross Profit ]],0) -> 21.5
A11: ORD-002165 | B11: 45938 | C11: SKU-0005 | D11: 1 | E11: 55.2 | F11: 0.05 | G11: 0 | H11: Online Store | I11: Wilmington | J11: Small Business | K11: Completed | L11: CUST-1316 | M11: Glass Food Containers | N11: Home & Kitchen | O11: 25.85 | P11: 55.2 | Q11: =Sales_Analysis[[#This Row],[Quantity]]*Sales_Analysis[[#This Row],[Unit Selling Price]] -> 55.2 | R11: =Sales_Analysis[[#This Row],[Gross Sales ]]*Sales_Analysis[[#This Row],[Discount Pct]] -> 2.76 | S11: =Sales_Analysis[[#This Row],[Gross Sales ]]-Sales_Analysis[[#This Row],[Discount Amount]] -> 52.44 | T11: =Sales_Analysis[[#This Row],[Quantity]]*Sales_Analysis[[#This Row],[Unit Cost]] -> 25.85 | U11: =Sales_Analysis[[#This Row],[Net Sales ]]-Sales_Analysis[[#This Row],[Cost Of Good Sold]] -> 26.59 | V11: =IF(Sales_Analysis[[#This Row],[Order Status]]="Completed",Sales_Analysis[[#This Row],[Net Sales ]],0) -> 52.44 | W11: =IF(Sales_Analysis[[#This Row],[Order Status]]="Completed",Sales_Analysis[[#This Row],[Gross Profit ]],0) -> 26.59
A12: ORD-002080 | B12: 45931 | C12: SKU-0037 | D12: 4 | E12: 25.18 | F12: 0 | G12: 6.99 | H12: Online Store | I12: Greensboro | J12: Consumer | K12: Completed | L12: CUST-1525 | M12: Notebook 3-Pack | N12: Office | O12: 13.85 | P12: 25.18 | Q12: =Sales_Analysis[[#This Row],[Quantity]]*Sales_Analysis[[#This Row],[Unit Selling Price]] -> 100.72 | R12: =Sales_Analysis[[#This Row],[Gross Sales ]]*Sales_Analysis[[#This Row],[Discount Pct]] -> 0 | S12: =Sales_Analysis[[#This Row],[Gross Sales ]]-Sales_Analysis[[#This Row],[Discount Amount]] -> 100.72 | T12: =Sales_Analysis[[#This Row],[Quantity]]*Sales_Analysis[[#This Row],[Unit Cost]] -> 55.4 | U12: =Sales_Analysis[[#This Row],[Net Sales ]]-Sales_Analysis[[#This Row],[Cost Of Good Sold]] -> 45.32 | V12: =IF(Sales_Analysis[[#This Row],[Order Status]]="Completed",Sales_Analysis[[#This Row],[Net Sales ]],0) -> 100.72 | W12: =IF(Sales_Analysis[[#This Row],[Order Status]]="Completed",Sales_Analysis[[#This Row],[Gross Profit ]],0) -> 45.32
A13: ORD-001822 | B13: 45940 | C13: SKU-0037 | D13: 1 | E13: 25.18 | F13: 0.15 | G13: 9.99 | H13: Marketplace | I13: Raleigh | J13: Small Business | K13: Completed | L13: CUST-1412 | M13: Notebook 3-Pack | N13: Office | O13: 13.85 | P13: 25.18 | Q13: =Sales_Analysis[[#This Row],[Quantity]]*Sales_Analysis[[#This Row],[Unit Selling Price]] -> 25.18 | R13: =Sales_Analysis[[#This Row],[Gross Sales ]]*Sales_Analysis[[#This Row],[Discount Pct]] -> 3.777 | S13: =Sales_Analysis[[#This Row],[Gross Sales ]]-Sales_Analysis[[#This Row],[Discount Amount]] -> 21.403 | T13: =Sales_Analysis[[#This Row],[Quantity]]*Sales_Analysis[[#This Row],[Unit Cost]] -> 13.85 | U13: =Sales_Analysis[[#This Row],[Net Sales ]]-Sales_Analysis[[#This Row],[Cost Of Good Sold]] -> 7.553 | V13: =IF(Sales_Analysis[[#This Row],[Order Status]]="Completed",Sales_Analysis[[#This Row],[Net Sales ]],0) -> 21.403 | W13: =IF(Sales_Analysis[[#This Row],[Order Status]]="Completed",Sales_Analysis[[#This Row],[Gross Profit ]],0) -> 7.553
... A2501: ORD-002407 | B2501: 46295 | C2501: SKU-0043 | D2501: 2 | E2501: 39.21 | F2501: 0 | G2501: 0 | H2501: Online Store | I2501: Wilmington | J2501: Small Business | K2501: Completed | L2501: CUST-1306 | M2501: Ergonomic Wrist Rest | N2501: Office | O2501: 19.66 | P2501: 39.21 | Q2501: =Sales_Analysis[[#This Row],[Quantity]]*Sales_Analysis[[#This Row],[Unit Selling Price]] -> 78.42 | R2501: =Sales_Analysis[[#This Row],[Gross Sales ]]*Sales_Analysis[[#This Row],[Discount Pct]] -> 0 | S2501: =Sales_Analysis[[#This Row],[Gross Sales ]]-Sales_Analysis[[#This Row],[Discount Amount]] -> 78.42 | T2501: =Sales_Analysis[[#This Row],[Quantity]]*Sales_Analysis[[#This Row],[Unit Cost]] -> 39.32 | U2501: =Sales_Analysis[[#This Row],[Net Sales ]]-Sales_Analysis[[#This Row],[Cost Of Good Sold]] -> 39.1 | V2501: =IF(Sales_Analysis[[#This Row],[Order Status]]="Completed",Sales_Analysis[[#This Row],[Net Sales ]],0) -> 78.42 | W2501: =IF(Sales_Analysis[[#This Row],[Order Status]]="Completed",Sales_Analysis[[#This Row],[Gross Profit ]],0) -> 39.1

Sheet Audit_Duplicate_OrderIDs
A1: Order ID | B1: RecordCount
A2: ORD-000021 | B2: 1
A3: ORD-000298 | B3: 1
A4: ORD-000479 | B4: 1
A5: ORD-001785 | B5: 1
A6: ORD-001801 | B6: 1
A7: ORD-002080 | B7: 1
A8: ORD-000270 | B8: 1
A9: ORD-000937 | B9: 1
A10: ORD-001847 | B10: 1
A11: ORD-002390 | B11: 1
A12: ORD-002492 | B12: 1
A13: ORD-001000 | B13: 1
... A2501: ORD-002407 | B2501: 1

Sheet PivotTables_KPI
A1: Market | B1: (All)
A3: Sum of Recognized Revenue | B3: Column Labels
A4: Row Labels | B4: Marketplace | C4: Online Store | D4: Retail Store | E4: Grand Total
A5: 2025 | B5: 23529.591 | C5: 19154.533 | D5: 17355.658 | E5: 60039.782
A6: Oct | B6: 7656.239 | C6: 5937.669 | D6: 5282.4905 | E6: 18876.399
A7: Nov | B7: 9028.6035 | C7: 6385.6105 | D7: 6228.099 | E7: 21642.313
A8: Dec | B8: 6844.7485 | C8: 6831.2535 | D8: 5845.0685 | E8: 19521.071
A9: 2026 | B9: 63740.411 | C9: 59632.362 | D9: 61711.652 | E9: 185084.43
A10: Jan | B10: 5699.0485 | C10: 5715.763 | D10: 6221.3665 | E10: 17636.178
A11: Feb | B11: 5265.188 | C11: 4781.35 | D11: 4590.9845 | E11: 14637.522
A12: Mar | B12: 6892.36 | C12: 8498.5575 | D12: 6170.6705 | E12: 21561.588
A13: Apr | B13: 6858.429 | C13: 8292.619 | D13: 6804.3835 | E13: 21955.431
A14: May | B14: 7751.563 | C14: 7280.119 | D14: 5869.7885 | E14: 20901.47
A15: Jun | B15: 9124.731 | C15: 4960.644 | D15: 9072.152 | E15: 23157.527
A16: Jul | B16: 7281.5995 | C16: 7053.022 | D16: 9888.662 | E16: 24223.284
... A19: Grand Total | B19: 87270.002 | C19: 78786.895 | D19: 79067.311 | E19: 245124.21
A22: Row Labels | B22: Revenue
A23: Accessories | B23: 59942.774
A24: Office | B24: 49552.261
A25: Fitness | B25: 49173.04
A26: Home & Kitchen | B26: 43267.339
A27: Electronics | B27: 43188.794
A28: Grand Total | B28: 245124.21
A35: Category | B35: (All)
A37: Row Labels | B37: Revenue | C37: Gross Profit
A38: Asheville | B38: 52370.586 | C38: 24565.237
A39: Charlotte | B39: 54719.787 | C39: 25815.708
A40: Greensboro | B40: 46023.509 | C40: 21656.509
A41: Raleigh | B41: 43558.119 | C41: 20642.649
A42: Wilmington | B42: 48452.206 | C42: 22974.145
A43: Grand Total | B43: 245124.21 | C43: 115654.25
A46: Row Labels | B46: Gross Profit | C46: Revenue | D46: Count of Order Status
A47: Cancelled | B47: 0 | C47: 0 | D47: 52
A48: Completed | B48: 115654.25 | C48: 245124.21 | D48: 2305
A49: Returned | B49: 0 | C49: 0 | D49: 143
A50: Grand Total | B50: 115654.25 | C50: 245124.21 | D50: 2500
A54: Row Labels | B54: Sum of Gross Profit
A55: Accessories | B55: 31599.083
A56: Electronics | B56: 21588.497
A57: Fitness | B57: 24194.401
A58: Home & Kitchen | B58: 23844.838
A59: Office | B59: 24639.425
A60: Grand Total | B60: 125866.25

Sheet Reorder Model
A1: SKU | B1: On-Hand | C1: On-Order | D1: Reserved | E1: Inventory Position | F1: Daily Demand | G1: Lead Time | H1: Safety Stock | I1: Reorder Point | J1: Suggested Order Qty | K1: Reorder Flag | L1: Target Stock | M1: Unit Cost | N1: Estimated Purchase Cost | O1: Estimated Days of Supply | P1: Stockout Risk | Q1: Product Name
A2: SKU-0001 | B2: =_xlfn.XLOOKUP(A2,InventorySnapShotCleaned!A:A,InventorySnapShotCleaned!B:B,"Not Found") -> 92 | C2: =_xlfn.XLOOKUP($A2,InventorySnapShotCleaned!$A:$A,InventorySnapShotCleaned!G:G,"Not Found") -> 24 | D2: =_xlfn.XLOOKUP($A2,InventorySnapShotCleaned!$A:$A,InventorySnapShotCleaned!H:H,"Not Found") -> 7 | E2: =B2+C2-D2 -> 109 | F2: =_xlfn.XLOOKUP($A2,InventorySnapShotCleaned!$A:$A,InventorySnapShotCleaned!E:E,"Not Found") -> 1.54 | G2: =_xlfn.XLOOKUP(_xlfn.XLOOKUP(A2,Products!A:A,Products!D:D),Suppliers!A:A,Suppliers!F:F) -> 5 | H2: =_xlfn.XLOOKUP($A2,InventorySnapShotCleaned!$A:$A,InventorySnapShotCleaned!C:C,"Not Found") -> 33 | I2: =ROUNDUP(F2*G2+H2,0) -> 41 | J2: =IF(E2<=I2,MAX(0,L2-E2),0) -> 0 | K2: =IF(E2<=I2,"REORDER","OK") -> OK | L2: =_xlfn.XLOOKUP(A2,InventorySnapShotCleaned!A:A,InventorySnapShotCleaned!D:D) -> 130 | M2: =_xlfn.XLOOKUP(A2,ProductsTableCleaned!A:A,ProductsTableCleaned!E:E) -> 13.79 | N2: =M2*J2 -> 0 | O2: =IFERROR(MAX(0,B2-D2)/F2,0) -> 55.194805 | P2: =IF(B2<D2,"BACKORDER",IF(F2<=0,"NO DEMAND",IF(O2<=3,"URGENT",IF(O2<G2,"AT RISK","COVERED")))) -> COVERED | Q2: =_xlfn.XLOOKUP(A2,Products!A:A,Products!B:B,"Not Found") -> Ceramic Dinnerware Set
A3: SKU-0002 | B3: =_xlfn.XLOOKUP(A3,InventorySnapShotCleaned!A:A,InventorySnapShotCleaned!B:B,"Not Found") -> 162 | C3: =_xlfn.XLOOKUP($A3,InventorySnapShotCleaned!$A:$A,InventorySnapShotCleaned!G:G,"Not Found") -> 24 | D3: =_xlfn.XLOOKUP($A3,InventorySnapShotCleaned!$A:$A,InventorySnapShotCleaned!H:H,"Not Found") -> 1 | E3: =B3+C3-D3 -> 185 | F3: =_xlfn.XLOOKUP($A3,InventorySnapShotCleaned!$A:$A,InventorySnapShotCleaned!E:E,"Not Found") -> 2.72 | G3: =_xlfn.XLOOKUP(_xlfn.XLOOKUP(A3,Products!A:A,Products!D:D),Suppliers!A:A,Suppliers!F:F) -> 6 | H3: =_xlfn.XLOOKUP($A3,InventorySnapShotCleaned!$A:$A,InventorySnapShotCleaned!C:C,"Not Found") -> 20 | I3: =ROUNDUP(F3*G3+H3,0) -> 37 | J3: =IF(E3<=I3,MAX(0,L3-E3),0) -> 0 | K3: =IF(E3<=I3,"REORDER","OK") -> OK | L3: =_xlfn.XLOOKUP(A3,InventorySnapShotCleaned!A:A,InventorySnapShotCleaned!D:D) -> 177 | M3: =_xlfn.XLOOKUP(A3,ProductsTableCleaned!A:A,ProductsTableCleaned!E:E) -> 37 | N3: =M3*J3 -> 0 | O3: =IFERROR(MAX(0,B3-D3)/F3,0) -> 59.191176 | P3: =IF(B3<D3,"BACKORDER",IF(F3<=0,"NO DEMAND",IF(O3<=3,"URGENT",IF(O3<G3,"AT RISK","COVERED")))) -> COVERED | Q3: =_xlfn.XLOOKUP(A3,Products!A:A,Products!B:B,"Not Found") -> Insulated Water Bottle
A4: SKU-0003 | B4: =_xlfn.XLOOKUP(A4,InventorySnapShotCleaned!A:A,InventorySnapShotCleaned!B:B,"Not Found") -> 180 | C4: =_xlfn.XLOOKUP($A4,InventorySnapShotCleaned!$A:$A,InventorySnapShotCleaned!G:G,"Not Found") -> 1 | D4: =_xlfn.XLOOKUP($A4,InventorySnapShotCleaned!$A:$A,InventorySnapShotCleaned!H:H,"Not Found") -> 8 | E4: =B4+C4-D4 -> 173 | F4: =_xlfn.XLOOKUP($A4,InventorySnapShotCleaned!$A:$A,InventorySnapShotCleaned!E:E,"Not Found") -> 0.48 | G4: =_xlfn.XLOOKUP(_xlfn.XLOOKUP(A4,Products!A:A,Products!D:D),Suppliers!A:A,Suppliers!F:F) -> 10 | H4: =_xlfn.XLOOKUP($A4,InventorySnapShotCleaned!$A:$A,InventorySnapShotCleaned!C:C,"Not Found") -> 22 | I4: =ROUNDUP(F4*G4+H4,0) -> 27 | J4: =IF(E4<=I4,MAX(0,L4-E4),0) -> 0 | K4: =IF(E4<=I4,"REORDER","OK") -> OK | L4: =_xlfn.XLOOKUP(A4,InventorySnapShotCleaned!A:A,InventorySnapShotCleaned!D:D) -> 140 | M4: =_xlfn.XLOOKUP(A4,ProductsTableCleaned!A:A,ProductsTableCleaned!E:E) -> 6.46 | N4: =M4*J4 -> 0 | O4: =IFERROR(MAX(0,B4-D4)/F4,0) -> 358.33333 | P4: =IF(B4<D4,"BACKORDER",IF(F4<=0,"NO DEMAND",IF(O4<=3,"URGENT",IF(O4<G4,"AT RISK","COVERED")))) -> COVERED | Q4: =_xlfn.XLOOKUP(A4,Products!A:A,Products!B:B,"Not Found") -> Nonstick Skillet
A5: SKU-0004 | B5: =_xlfn.XLOOKUP(A5,InventorySnapShotCleaned!A:A,InventorySnapShotCleaned!B:B,"Not Found") -> 213 | C5: =_xlfn.XLOOKUP($A5,InventorySnapShotCleaned!$A:$A,InventorySnapShotCleaned!G:G,"Not Found") -> 21 | D5: =_xlfn.XLOOKUP($A5,InventorySnapShotCleaned!$A:$A,InventorySnapShotCleaned!H:H,"Not Found") -> 9 | E5: =B5+C5-D5 -> 225 | F5: =_xlfn.XLOOKUP($A5,InventorySnapShotCleaned!$A:$A,InventorySnapShotCleaned!E:E,"Not Found") -> 2.04 | G5: =_xlfn.XLOOKUP(_xlfn.XLOOKUP(A5,Products!A:A,Products!D:D),Suppliers!A:A,Suppliers!F:F) -> 5 | H5: =_xlfn.XLOOKUP($A5,InventorySnapShotCleaned!$A:$A,InventorySnapShotCleaned!C:C,"Not Found") -> 35 | I5: =ROUNDUP(F5*G5+H5,0) -> 46 | J5: =IF(E5<=I5,MAX(0,L5-E5),0) -> 0 | K5: =IF(E5<=I5,"REORDER","OK") -> OK | L5: =_xlfn.XLOOKUP(A5,InventorySnapShotCleaned!A:A,InventorySnapShotCleaned!D:D) -> 82 | M5: =_xlfn.XLOOKUP(A5,ProductsTableCleaned!A:A,ProductsTableCleaned!E:E) -> 11.55 | N5: =M5*J5 -> 0 | O5: =IFERROR(MAX(0,B5-D5)/F5,0) -> 100 | P5: =IF(B5<D5,"BACKORDER",IF(F5<=0,"NO DEMAND",IF(O5<=3,"URGENT",IF(O5<G5,"AT RISK","COVERED")))) -> COVERED | Q5: =_xlfn.XLOOKUP(A5,Products!A:A,Products!B:B,"Not Found") -> Bamboo Cutting Board
A6: SKU-0005 | B6: =_xlfn.XLOOKUP(A6,InventorySnapShotCleaned!A:A,InventorySnapShotCleaned!B:B,"Not Found") -> 33 | C6: =_xlfn.XLOOKUP($A6,InventorySnapShotCleaned!$A:$A,InventorySnapShotCleaned!G:G,"Not Found") -> 20 | D6: =_xlfn.XLOOKUP($A6,InventorySnapShotCleaned!$A:$A,InventorySnapShotCleaned!H:H,"Not Found") -> 8 | E6: =B6+C6-D6 -> 45 | F6: =_xlfn.XLOOKUP($A6,InventorySnapShotCleaned!$A:$A,InventorySnapShotCleaned!E:E,"Not Found") -> 1.28 | G6: =_xlfn.XLOOKUP(_xlfn.XLOOKUP(A6,Products!A:A,Products!D:D),Suppliers!A:A,Suppliers!F:F) -> 5 | H6: =_xlfn.XLOOKUP($A6,InventorySnapShotCleaned!$A:$A,InventorySnapShotCleaned!C:C,"Not Found") -> 22 | I6: =ROUNDUP(F6*G6+H6,0) -> 29 | J6: =IF(E6<=I6,MAX(0,L6-E6),0) -> 0 | K6: =IF(E6<=I6,"REORDER","OK") -> OK | L6: =_xlfn.XLOOKUP(A6,InventorySnapShotCleaned!A:A,InventorySnapShotCleaned!D:D) -> 175 | M6: =_xlfn.XLOOKUP(A6,ProductsTableCleaned!A:A,ProductsTableCleaned!E:E) -> 25.85 | N6: =M6*J6 -> 0 | O6: =IFERROR(MAX(0,B6-D6)/F6,0) -> 19.53125 | P6: =IF(B6<D6,"BACKORDER",IF(F6<=0,"NO DEMAND",IF(O6<=3,"URGENT",IF(O6<G6,"AT RISK","COVERED")))) -> COVERED | Q6: =_xlfn.XLOOKUP(A6,Products!A:A,Products!B:B,"Not Found") -> Glass Food Containers
A7: SKU-0006 | B7: =_xlfn.XLOOKUP(A7,InventorySnapShotCleaned!A:A,InventorySnapShotCleaned!B:B,"Not Found") -> 153 | C7: =_xlfn.XLOOKUP($A7,InventorySnapShotCleaned!$A:$A,InventorySnapShotCleaned!G:G,"Not Found") -> 9 | D7: =_xlfn.XLOOKUP($A7,InventorySnapShotCleaned!$A:$A,InventorySnapShotCleaned!H:H,"Not Found") -> 5 | E7: =B7+C7-D7 -> 157 | F7: =_xlfn.XLOOKUP($A7,InventorySnapShotCleaned!$A:$A,InventorySnapShotCleaned!E:E,"Not Found") -> 1.13 | G7: =_xlfn.XLOOKUP(_xlfn.XLOOKUP(A7,Products!A:A,Products!D:D),Suppliers!A:A,Suppliers!F:F) -> 6 | H7: =_xlfn.XLOOKUP($A7,InventorySnapShotCleaned!$A:$A,InventorySnapShotCleaned!C:C,"Not Found") -> 23 | I7: =ROUNDUP(F7*G7+H7,0) -> 30 | J7: =IF(E7<=I7,MAX(0,L7-E7),0) -> 0 | K7: =IF(E7<=I7,"REORDER","OK") -> OK | L7: =_xlfn.XLOOKUP(A7,InventorySnapShotCleaned!A:A,InventorySnapShotCleaned!D:D) -> 190 | M7: =_xlfn.XLOOKUP(A7,ProductsTableCleaned!A:A,ProductsTableCleaned!E:E) -> 21.34 | N7: =M7*J7 -> 0 | O7: =IFERROR(MAX(0,B7-D7)/F7,0) -> 130.97345 | P7: =IF(B7<D7,"BACKORDER",IF(F7<=0,"NO DEMAND",IF(O7<=3,"URGENT",IF(O7<G7,"AT RISK","COVERED")))) -> COVERED | Q7: =_xlfn.XLOOKUP(A7,Products!A:A,Products!B:B,"Not Found") -> Kitchen Scale
A8: SKU-0007 | B8: =_xlfn.XLOOKUP(A8,InventorySnapShotCleaned!A:A,InventorySnapShotCleaned!B:B,"Not Found") -> 21 | C8: =_xlfn.XLOOKUP($A8,InventorySnapShotCleaned!$A:$A,InventorySnapShotCleaned!G:G,"Not Found") -> 8 | D8: =_xlfn.XLOOKUP($A8,InventorySnapShotCleaned!$A:$A,InventorySnapShotCleaned!H:H,"Not Found") -> 0 | E8: =B8+C8-D8 -> 29 | F8: =_xlfn.XLOOKUP($A8,InventorySnapShotCleaned!$A:$A,InventorySnapShotCleaned!E:E,"Not Found") -> 3.29 | G8: =_xlfn.XLOOKUP(_xlfn.XLOOKUP(A8,Products!A:A,Products!D:D),Suppliers!A:A,Suppliers!F:F) -> 6 | H8: =_xlfn.XLOOKUP($A8,InventorySnapShotCleaned!$A:$A,InventorySnapShotCleaned!C:C,"Not Found") -> 31 | I8: =ROUNDUP(F8*G8+H8,0) -> 51 | J8: =IF(E8<=I8,MAX(0,L8-E8),0) -> 103 | K8: =IF(E8<=I8,"REORDER","OK") -> REORDER | L8: =_xlfn.XLOOKUP(A8,InventorySnapShotCleaned!A:A,InventorySnapShotCleaned!D:D) -> 132 | M8: =_xlfn.XLOOKUP(A8,ProductsTableCleaned!A:A,ProductsTableCleaned!E:E) -> 7.24 | N8: =M8*J8 -> 745.72 | O8: =IFERROR(MAX(0,B8-D8)/F8,0) -> 6.3829787 | P8: =IF(B8<D8,"BACKORDER",IF(F8<=0,"NO DEMAND",IF(O8<=3,"URGENT",IF(O8<G8,"AT RISK","COVERED")))) -> COVERED | Q8: =_xlfn.XLOOKUP(A8,Products!A:A,Products!B:B,"Not Found") -> Cotton Bath Towels
A9: SKU-0008 | B9: =_xlfn.XLOOKUP(A9,InventorySnapShotCleaned!A:A,InventorySnapShotCleaned!B:B,"Not Found") -> 142 | C9: =_xlfn.XLOOKUP($A9,InventorySnapShotCleaned!$A:$A,InventorySnapShotCleaned!G:G,"Not Found") -> 7 | D9: =_xlfn.XLOOKUP($A9,InventorySnapShotCleaned!$A:$A,InventorySnapShotCleaned!H:H,"Not Found") -> 6 | E9: =B9+C9-D9 -> 143 | F9: =_xlfn.XLOOKUP($A9,InventorySnapShotCleaned!$A:$A,InventorySnapShotCleaned!E:E,"Not Found") -> 2.42 | G9: =_xlfn.XLOOKUP(_xlfn.XLOOKUP(A9,Products!A:A,Products!D:D),Suppliers!A:A,Suppliers!F:F) -> 6 | H9: =_xlfn.XLOOKUP($A9,InventorySnapShotCleaned!$A:$A,InventorySnapShotCleaned!C:C,"Not Found") -> 28 | I9: =ROUNDUP(F9*G9+H9,0) -> 43 | J9: =IF(E9<=I9,MAX(0,L9-E9),0) -> 0 | K9: =IF(E9<=I9,"REORDER","OK") -> OK | L9: =_xlfn.XLOOKUP(A9,InventorySnapShotCleaned!A:A,InventorySnapShotCleaned!D:D) -> 223 | M9: =_xlfn.XLOOKUP(A9,ProductsTableCleaned!A:A,ProductsTableCleaned!E:E) -> 13.1 | N9: =M9*J9 -> 0 | O9: =IFERROR(MAX(0,B9-D9)/F9,0) -> 56.198347 | P9: =IF(B9<D9,"BACKORDER",IF(F9<=0,"NO DEMAND",IF(O9<=3,"URGENT",IF(O9<G9,"AT RISK","COVERED")))) -> COVERED | Q9: =_xlfn.XLOOKUP(A9,Products!A:A,Products!B:B,"Not Found") -> LED Desk Lamp
A10: SKU-0009 | B10: =_xlfn.XLOOKUP(A10,InventorySnapShotCleaned!A:A,InventorySnapShotCleaned!B:B,"Not Found") -> 71 | C10: =_xlfn.XLOOKUP($A10,InventorySnapShotCleaned!$A:$A,InventorySnapShotCleaned!G:G,"Not Found") -> 24 | D10: =_xlfn.XLOOKUP($A10,InventorySnapShotCleaned!$A:$A,InventorySnapShotCleaned!H:H,"Not Found") -> 6 | E10: =B10+C10-D10 -> 89 | F10: =_xlfn.XLOOKUP($A10,InventorySnapShotCleaned!$A:$A,InventorySnapShotCleaned!E:E,"Not Found") -> 0.4 | G10: =_xlfn.XLOOKUP(_xlfn.XLOOKUP(A10,Products!A:A,Products!D:D),Suppliers!A:A,Suppliers!F:F) -> 6 | H10: =_xlfn.XLOOKUP($A10,InventorySnapShotCleaned!$A:$A,InventorySnapShotCleaned!C:C,"Not Found") -> 28 | I10: =ROUNDUP(F10*G10+H10,0) -> 31 | J10: =IF(E10<=I10,MAX(0,L10-E10),0) -> 0 | K10: =IF(E10<=I10,"REORDER","OK") -> OK | L10: =_xlfn.XLOOKUP(A10,InventorySnapShotCleaned!A:A,InventorySnapShotCleaned!D:D) -> 209 | M10: =_xlfn.XLOOKUP(A10,ProductsTableCleaned!A:A,ProductsTableCleaned!E:E) -> 36.44 | N10: =M10*J10 -> 0 | O10: =IFERROR(MAX(0,B10-D10)/F10,0) -> 162.5 | P10: =IF(B10<D10,"BACKORDER",IF(F10<=0,"NO DEMAND",IF(O10<=3,"URGENT",IF(O10<G10,"AT RISK","COVERED")))) -> COVERED | Q10: =_xlfn.XLOOKUP(A10,Products!A:A,Products!B:B,"Not Found") -> Storage Bin Set
A11: SKU-0010 | B11: =_xlfn.XLOOKUP(A11,InventorySnapShotCleaned!A:A,InventorySnapShotCleaned!B:B,"Not Found") -> 8 | C11: =_xlfn.XLOOKUP($A11,InventorySnapShotCleaned!$A:$A,InventorySnapShotCleaned!G:G,"Not Found") -> 19 | D11: =_xlfn.XLOOKUP($A11,InventorySnapShotCleaned!$A:$A,InventorySnapShotCleaned!H:H,"Not Found") -> 9 | E11: =B11+C11-D11 -> 18 | F11: =_xlfn.XLOOKUP($A11,InventorySnapShotCleaned!$A:$A,InventorySnapShotCleaned!E:E,"Not Found") -> 0.79 | G11: =_xlfn.XLOOKUP(_xlfn.XLOOKUP(A11,Products!A:A,Products!D:D),Suppliers!A:A,Suppliers!F:F) -> 10 | H11: =_xlfn.XLOOKUP($A11,InventorySnapShotCleaned!$A:$A,InventorySnapShotCleaned!C:C,"Not Found") -> 14 | I11: =ROUNDUP(F11*G11+H11,0) -> 22 | J11: =IF(E11<=I11,MAX(0,L11-E11),0) -> 131 | K11: =IF(E11<=I11,"REORDER","OK") -> REORDER | L11: =_xlfn.XLOOKUP(A11,InventorySnapShotCleaned!A:A,InventorySnapShotCleaned!D:D) -> 149 | M11: =_xlfn.XLOOKUP(A11,ProductsTableCleaned!A:A,ProductsTableCleaned!E:E) -> 8.53 | N11: =M11*J11 -> 1117.43 | O11: =IFERROR(MAX(0,B11-D11)/F11,0) -> 0 | P11: =IF(B11<D11,"BACKORDER",IF(F11<=0,"NO DEMAND",IF(O11<=3,"URGENT",IF(O11<G11,"AT RISK","COVERED")))) -> BACKORDER | Q11: =_xlfn.XLOOKUP(A11,Products!A:A,Products!B:B,"Not Found") -> Throw Blanket
A12: SKU-0011 | B12: =_xlfn.XLOOKUP(A12,InventorySnapShotCleaned!A:A,InventorySnapShotCleaned!B:B,"Not Found") -> 122 | C12: =_xlfn.XLOOKUP($A12,InventorySnapShotCleaned!$A:$A,InventorySnapShotCleaned!G:G,"Not Found") -> 6 | D12: =_xlfn.XLOOKUP($A12,InventorySnapShotCleaned!$A:$A,InventorySnapShotCleaned!H:H,"Not Found") -> 7 | E12: =B12+C12-D12 -> 121 | F12: =_xlfn.XLOOKUP($A12,InventorySnapShotCleaned!$A:$A,InventorySnapShotCleaned!E:E,"Not Found") -> 1.87 | G12: =_xlfn.XLOOKUP(_xlfn.XLOOKUP(A12,Products!A:A,Products!D:D),Suppliers!A:A,Suppliers!F:F) -> 10 | H12: =_xlfn.XLOOKUP($A12,InventorySnapShotCleaned!$A:$A,InventorySnapShotCleaned!C:C,"Not Found") -> 24 | I12: =ROUNDUP(F12*G12+H12,0) -> 43 | J12: =IF(E12<=I12,MAX(0,L12-E12),0) -> 0 | K12: =IF(E12<=I12,"REORDER","OK") -> OK | L12: =_xlfn.XLOOKUP(A12,InventorySnapShotCleaned!A:A,InventorySnapShotCleaned!D:D) -> 161 | M12: =_xlfn.XLOOKUP(A12,ProductsTableCleaned!A:A,ProductsTableCleaned!E:E) -> 24.06 | N12: =M12*J12 -> 0 | O12: =IFERROR(MAX(0,B12-D12)/F12,0) -> 61.497326 | P12: =IF(B12<D12,"BACKORDER",IF(F12<=0,"NO DEMAND",IF(O12<=3,"URGENT",IF(O12<G12,"AT RISK","COVERED")))) -> COVERED | Q12: =_xlfn.XLOOKUP(A12,Products!A:A,Products!B:B,"Not Found") -> French Press
A13: SKU-0012 | B13: =_xlfn.XLOOKUP(A13,InventorySnapShotCleaned!A:A,InventorySnapShotCleaned!B:B,"Not Found") -> 188 | C13: =_xlfn.XLOOKUP($A13,InventorySnapShotCleaned!$A:$A,InventorySnapShotCleaned!G:G,"Not Found") -> 3 | D13: =_xlfn.XLOOKUP($A13,InventorySnapShotCleaned!$A:$A,InventorySnapShotCleaned!H:H,"Not Found") -> 3 | E13: =B13+C13-D13 -> 188 | F13: =_xlfn.XLOOKUP($A13,InventorySnapShotCleaned!$A:$A,InventorySnapShotCleaned!E:E,"Not Found") -> 3.19 | G13: =_xlfn.XLOOKUP(_xlfn.XLOOKUP(A13,Products!A:A,Products!D:D),Suppliers!A:A,Suppliers!F:F) -> 10 | H13: =_xlfn.XLOOKUP($A13,InventorySnapShotCleaned!$A:$A,InventorySnapShotCleaned!C:C,"Not Found") -> 22 | I13: =ROUNDUP(F13*G13+H13,0) -> 54 | J13: =IF(E13<=I13,MAX(0,L13-E13),0) -> 0 | K13: =IF(E13<=I13,"REORDER","OK") -> OK | L13: =_xlfn.XLOOKUP(A13,InventorySnapShotCleaned!A:A,InventorySnapShotCleaned!D:D) -> 116 | M13: =_xlfn.XLOOKUP(A13,ProductsTableCleaned!A:A,ProductsTableCleaned!E:E) -> 34.53 | N13: =M13*J13 -> 0 | O13: =IFERROR(MAX(0,B13-D13)/F13,0) -> 57.99373 | P13: =IF(B13<D13,"BACKORDER",IF(F13<=0,"NO DEMAND",IF(O13<=3,"URGENT",IF(O13<G13,"AT RISK","COVERED")))) -> COVERED | Q13: =_xlfn.XLOOKUP(A13,Products!A:A,Products!B:B,"Not Found") -> Portable Blender
... A61: SKU-0060 | B61: =_xlfn.XLOOKUP(A61,InventorySnapShotCleaned!A:A,InventorySnapShotCleaned!B:B,"Not Found") -> 151 | C61: =_xlfn.XLOOKUP($A61,InventorySnapShotCleaned!$A:$A,InventorySnapShotCleaned!G:G,"Not Found") -> 13 | D61: =_xlfn.XLOOKUP($A61,InventorySnapShotCleaned!$A:$A,InventorySnapShotCleaned!H:H,"Not Found") -> 6 | E61: =B61+C61-D61 -> 158 | F61: =_xlfn.XLOOKUP($A61,InventorySnapShotCleaned!$A:$A,InventorySnapShotCleaned!E:E,"Not Found") -> 1.32 | G61: =_xlfn.XLOOKUP(_xlfn.XLOOKUP(A61,Products!A:A,Products!D:D),Suppliers!A:A,Suppliers!F:F) -> 13 | H61: =_xlfn.XLOOKUP($A61,InventorySnapShotCleaned!$A:$A,InventorySnapShotCleaned!C:C,"Not Found") -> 32 | I61: =ROUNDUP(F61*G61+H61,0) -> 50 | J61: =IF(E61<=I61,MAX(0,L61-E61),0) -> 0 | K61: =IF(E61<=I61,"REORDER","OK") -> OK | L61: =_xlfn.XLOOKUP(A61,InventorySnapShotCleaned!A:A,InventorySnapShotCleaned!D:D) -> 127 | M61: =_xlfn.XLOOKUP(A61,ProductsTableCleaned!A:A,ProductsTableCleaned!E:E) -> 31.07 | N61: =M61*J61 -> 0 | O61: =IFERROR(MAX(0,B61-D61)/F61,0) -> 109.84848 | P61: =IF(B61<D61,"BACKORDER",IF(F61<=0,"NO DEMAND",IF(O61<=3,"URGENT",IF(O61<G61,"AT RISK","COVERED")))) -> COVERED | Q61: =_xlfn.XLOOKUP(A61,Products!A:A,Products!B:B,"Not Found") -> Luggage Tag Set

Sheet KPI Summary
A1: Retail Operations Dashboard
A3: Sales Performance | October 2025 – September 2026
A6: Sales Performance KPIs
A7: Total Revenue | B7: =GETPIVOTDATA("Revenue",PivotTables_KPI!$A$46) -> 245124.21
A8: Total Gross Profit | B8: =GETPIVOTDATA("Gross Profit",PivotTables_KPI!$A$46) -> 115654.25
A9: Gross Profit Margin | B9: =IFERROR(B8/B7,"Error") -> 0.47181896
A10: Completed Orders | B10: =GETPIVOTDATA("Count of Order Status",PivotTables_KPI!$A$46,"Order Status","Completed") -> 2305
A11: Average Order Value | B11: =IFERROR(B7/B10,0) -> 106.34456

Sheet Inventory Dashboard
A1: Inventory Dashboard
A3: Inventory KPIs
A4: Total Units to Purchase: | B4: =SUM('Reorder Model'!J2:J61) -> 707
A5: Estimated Purchasing Cost: | B5: =SUM('Reorder Model'!N2:N61) -> 13334.2
A6: Products Not Requiring Reorder: | B6: =COUNTIF('Reorder Model'!K2:K61,"OK") -> 54
A7: Urgent / Backorder Products: | B7: =COUNTIF('Reorder Model'!P2:P61,"URGENT")+COUNTIF('Reorder Model'!P2:P61,"BACKORDER") -> 1
A10: Inventory Risk Summary
A11: Risk Category | B11: Product Count
A12: BACKORDER | B12: =COUNTIF('Reorder Model'!$P$2:$P$61,A12) -> 1
A13: URGENT | B13: =COUNTIF('Reorder Model'!$P$2:$P$61,A13) -> 0
A14: AT RISK | B14: =COUNTIF('Reorder Model'!$P$2:$P$61,A14) -> 2
A15: COVERED | B15: =COUNTIF('Reorder Model'!$P$2:$P$61,A15) -> 57
A16: NO DEMAND | B16: =COUNTIF('Reorder Model'!$P$2:$P$61,A16) -> 0
A18: Products Requiring Reorder
A19: SKU | B19: Product Name | C19: Stockout Risk | D19: Days of Supply | E19: Suggested Order Qty | F19: Unit Cost | G19: Purchase Cost | H19: Priority
A20: {=_xlfn.LET(_xlpm.data,_xlfn.HSTACK(_xlfn.ANCHORARRAY('Purchasing Calculations'!A2),_xlfn.ANCHORARRAY('Purchasing Calculations'!B2),_xlfn.ANCHORARRAY('Purchasing Calculations'!C2),_xlfn.ANCHORARRAY('Purchasing Calculations'!D2),_xlfn.ANCHORARRAY('Purchasing Calculations'!E2),_xlfn.ANCHORARRAY('Purchasing Calculations'!F2),_xlfn.ANCHORARRAY('Purchasing Calculations'!G2),_xlfn.ANCHORARRAY('Purchasing Calculations'!H2)),_xlfn.SORTBY(_xlpm.data,_xlfn.CHOOSECOLS(_xlpm.data,8),1))} -> SKU-0010 | B20: Throw Blanket | C20: BACKORDER | D20: 0 | E20: 131 | F20: 8.53 | G20: 1117.43 | H20: 1
A21: SKU-0015 | B21: Bluetooth Speaker | C21: AT RISK | D21: 7.9365079 | E21: 141 | F21: 14.4 | G21: 2030.4 | H21: 3
A22: SKU-0017 | B22: Wireless Mouse | C22: AT RISK | D22: 6.9124424 | E22: 62 | F22: 31.21 | G22: 1935.02 | H22: 3
A23: SKU-0007 | B23: Cotton Bath Towels | C23: COVERED | D23: 6.3829787 | E23: 103 | F23: 7.24 | G23: 745.72 | H23: 4
A24: SKU-0036 | B24: Stretching Strap | C24: COVERED | D24: 40.677966 | E24: 133 | F24: 37.14 | G24: 4939.62 | H24: 4
A25: SKU-0052 | B25: Sunglasses | C25: COVERED | D25: 15.302491 | E25: 137 | F25: 18.73 | G25: 2566.01 | H25: 4

Sheet ReadMe
A1: Retail Operations & Inventory Analytics
A3: Project Overview
A5: I built this Excel project to practice data analytics and systems analysis using a simulated retail business. I'm studying Management Information Systems and Finance/Accounting at UNC Charlotte, and I wanted to create something that went beyond a basic Excel dashboard.
A7: The project focuses on two business problems: understanding sales performance and improving inventory purchasing decisions. My goal was to build a system that could analyze historical sales data while also helping a purchasing manager identify products that need to be reordered.
A9: All data used in this project is fictional and intended for educational purposes.
A11: Tools and Skills
A13: Microsoft Excel: Advanced formulas, PivotTables, PivotCharts, and dashboards
A15: Power Query: Data cleaning, transformations, and merging datasets
A17: XLOOKUP: Connecting product, inventory, and supplier information
A19: FILTER, SORTBY, and dynamic arrays: Automatically updating purchasing recommendations
A21: IF, SUMIFS, COUNTIF, and other formulas: Financial calculations and inventory rules
A23: What I Built
... A87: Building both dashboards helped me see the connection between data analytics and systems analysis. The sales dashboard explains what happened, while the inventory model uses business rules to help determine what should happen next.

Sheet Purchasing Calculations
A1: SKU | B1: Product Name | C1: Stockout Risk | D1: Days of Supply | E1: Suggested Order Qty | F1: Unit Cost | G1: Purchase Cost | H1: Priority
A2: {=_xlfn._xlws.FILTER('Reorder Model'!A2:A61,'Reorder Model'!K2:K61="REORDER","No products")} -> SKU-0007 | B2: {=_xlfn.XLOOKUP(_xlfn.ANCHORARRAY(A2),Products!A:A,Products!B:B,"Not Found")} -> Cotton Bath Towels | C2: {=_xlfn.XLOOKUP(_xlfn.ANCHORARRAY(A2),'Reorder Model'!A:A,'Reorder Model'!P:P,"Not Found")} -> COVERED | D2: {=_xlfn.XLOOKUP(_xlfn.ANCHORARRAY(A2),'Reorder Model'!A:A,'Reorder Model'!O:O,"Not Found")} -> 6.3829787 | E2: {=_xlfn.XLOOKUP(_xlfn.ANCHORARRAY(A2),'Reorder Model'!A:A,'Reorder Model'!J:J,"Not Found")} -> 103 | F2: {=_xlfn.XLOOKUP(_xlfn.ANCHORARRAY(A2),'Reorder Model'!A:A,'Reorder Model'!M:M,"Not Found")} -> 7.24 | G2: {=_xlfn.ANCHORARRAY(E2)*_xlfn.ANCHORARRAY(F2)} -> 745.72 | H2: {=_xlfn.SWITCH(_xlfn.ANCHORARRAY(C2),"BACKORDER",1,"URGENT",2,"AT RISK",3,"COVERED",4,"NO DEMAND",5,99)} -> 4
A3: SKU-0010 | B3: Throw Blanket | C3: BACKORDER | D3: 0 | E3: 131 | F3: 8.53 | G3: 1117.43 | H3: 1
A4: SKU-0015 | B4: Bluetooth Speaker | C4: AT RISK | D4: 7.9365079 | E4: 141 | F4: 14.4 | G4: 2030.4 | H4: 3
A5: SKU-0017 | B5: Wireless Mouse | C5: AT RISK | D5: 6.9124424 | E5: 62 | F5: 31.21 | G5: 1935.02 | H5: 3
A6: SKU-0036 | B6: Stretching Strap | C6: COVERED | D6: 40.677966 | E6: 133 | F6: 37.14 | G6: 4939.62 | H6: 4
A7: SKU-0052 | B7: Sunglasses | C7: COVERED | D7: 15.302491 | E7: 137 | F7: 18.73 | G7: 2566.01 | H7: 4
